Workbook
Name IncCCD1: 'Scenario Inputs'!$G$61
Name IncCCD2: 'Scenario Inputs'!$G$62
Name IncCCD3: 'Scenario Inputs'!$G$63
Name IncCCD4: 'Scenario Inputs'!$G$64
Name IncCCD5: 'Scenario Inputs'!$G$65
Name IncCCD6: 'Scenario Inputs'!$G$66
Name IncHHD: 'Cost Inputs'!#REF!
Name IncHHD: 'Scenario Inputs'!$G$49
Name IncLP: 'Scenario Inputs'!$G$67
Name IncPD: 'Scenario Inputs'!$G$52
Name IncPEcad: 'Scenario Inputs'!$G$97
Name IncPElive: 'Scenario Inputs'!$G$94

Sheet Cover Sheet

Sheet Background

Sheet DES Pathway Map

Sheet Costing Map

Sheet Methods Overview

Sheet simPy_sheet
A2: simulation duration | B2: =('Scenario Inputs'!R23-'Scenario Inputs'!R21)*365 + 365 -> 4745 | C2: days | D2: Region | E2: ='Scenario Inputs'!F20 -> Fictional Region | F2: Centre | G2: ='Scenario Inputs'!F21 -> Fictional Centre | P2: CURRENTLY PULLING THESE VALUES
P3: NEED TO ADD THESE
B4: 1 | C4: 2 | D4: 3 | E4: 4 | F4: 5 | G4: 6 | H4: 7 | I4: 8 | J4: 9 | K4: 10 | L4: 11 | M4: 12 | N4: 13
A5: Incidence Profile | B5: =daily_rate!A2 -> 0.5 | C5: =daily_rate!B2 -> 0.5 | D5: =daily_rate!C2 -> 0.5 | E5: =daily_rate!D2 -> 0.5 | F5: =daily_rate!E2 -> 0.5 | G5: =daily_rate!F2 -> 0.5 | H5: =daily_rate!G2 -> 0.5 | I5: =daily_rate!H2 -> 0.5 | ... N5: =daily_rate!M2 -> 0.5 | O5: validation
B6: =IF('Scenario Inputs'!I38="",daily_rate!N2,daily_rate!N2) -> 0.5 | C6: =IF('Scenario Inputs'!J38="",daily_rate!O2,daily_rate!O2) -> 0.5 | D6: =IF('Scenario Inputs'!K38="",daily_rate!P2,daily_rate!P2) -> 0.5 | E6: =IF('Scenario Inputs'!L38="",daily_rate!Q2,daily_rate!Q2) -> 0.5 | F6: =IF('Scenario Inputs'!M38="",daily_rate!R2,daily_rate!R2) -> 0.5 | G6: =IF('Scenario Inputs'!N38="",daily_rate!S2,daily_rate!S2) -> 0.5 | H6: =IF('Scenario Inputs'!O38="",daily_rate!T2,daily_rate!T2) -> 0.5 | I6: =IF('Scenario Inputs'!P38="",daily_rate!U2,daily_rate!U2) -> 0.5 | ... N6: =IF('Scenario Inputs'!U38="",daily_rate!Z2,daily_rate!Z2) -> 0.5 | O6: experimentation
A7: Age dist | B7: 1 | C7: 2 | D7: 3 | E7: 4 | F7: 5 | G7: 6
B8: =age_dist!B1 -> 0.05 | C8: =age_dist!B2 -> 0.07 | D8: =age_dist!B3 -> 0.12 | E8: =age_dist!B4 -> 0.2 | F8: =age_dist!B5 -> 0.25 | G8: =age_dist!B6 -> 0.31
A10: Referral | B10: Early | C10: Late
B11: =1-B12 -> 0.8 | C11: =1-C12 -> 0.8 | D11: =1-D12 -> 0.8 | E11: =1-E12 -> 0.8 | F11: =1-F12 -> 0.8 | G11: =1-G12 -> 0.8 | H11: =1-H12 -> 0.8 | I11: =1-I12 -> 0.8 | ... N11: =1-N12 -> 0.8
B12: =IF('Scenario Inputs'!I67="",referral_dist!$B$2,'Scenario Inputs'!I67) -> 0.2 | C12: =IF('Scenario Inputs'!J67="",referral_dist!$B$2,'Scenario Inputs'!J67) -> 0.2 | D12: =IF('Scenario Inputs'!K67="",referral_dist!$B$2,'Scenario Inputs'!K67) -> 0.2 | E12: =IF('Scenario Inputs'!L67="",referral_dist!$B$2,'Scenario Inputs'!L67) -> 0.2 | F12: =IF('Scenario Inputs'!M67="",referral_dist!$B$2,'Scenario Inputs'!M67) -> 0.2 | G12: =IF('Scenario Inputs'!N67="",referral_dist!$B$2,'Scenario Inputs'!N67) -> 0.2 | H12: =IF('Scenario Inputs'!O67="",referral_dist!$B$2,'Scenario Inputs'!O67) -> 0.2 | I12: =IF('Scenario Inputs'!P67="",referral_dist!$B$2,'Scenario Inputs'!P67) -> 0.2 | ... N12: =IF('Scenario Inputs'!U67="",referral_dist!$B$2,'Scenario Inputs'!U67) -> 0.2
A13: Interventions
B14: Rollout year target percentage
B15: 1 | C15: 2 | D15: 3 | E15: 4 | F15: 5 | G15: 6 | H15: 7 | I15: 8 | J15: 9 | K15: 10 | L15: 11 | M15: 12 | N15: 13
A16: Change in HHD allocation probability | B16: =IF('Scenario Inputs'!I49="",IncHHD,'Scenario Inputs'!I49) -> 0.18918919 | C16: =IF('Scenario Inputs'!J49="",IncHHD,'Scenario Inputs'!J49) -> 0.18918919 | D16: =IF('Scenario Inputs'!K49="",IncHHD,'Scenario Inputs'!K49) -> 0.18918919 | E16: =IF('Scenario Inputs'!L49="",IncHHD,'Scenario Inputs'!L49) -> 0.18918919 | F16: =IF('Scenario Inputs'!M49="",IncHHD,'Scenario Inputs'!M49) -> 0.18918919 | G16: =IF('Scenario Inputs'!N49="",IncHHD,'Scenario Inputs'!N49) -> 0.18918919 | H16: =IF('Scenario Inputs'!O49="",IncHHD,'Scenario Inputs'!O49) -> 0.18918919 | I16: =IF('Scenario Inputs'!P49="",IncHHD,'Scenario Inputs'!P49) -> 0.18918919 | ... N16: =IF('Scenario Inputs'!U49="",IncHHD,'Scenario Inputs'!U49) -> 0.18918919
A17: Change in PD allocation probability | B17: {=IF('Scenario Inputs'!I52="",IncPD,'Scenario Inputs'!I52)} -> 0.29 | C17: {=IF('Scenario Inputs'!J52="",IncPD,'Scenario Inputs'!J52)} -> 0.29 | D17: {=IF('Scenario Inputs'!K52="",IncPD,'Scenario Inputs'!K52)} -> 0.29 | E17: {=IF('Scenario Inputs'!L52="",IncPD,'Scenario Inputs'!L52)} -> 0.29 | F17: {=IF('Scenario Inputs'!M52="",IncPD,'Scenario Inputs'!M52)} -> 0.29 | G17: {=IF('Scenario Inputs'!N52="",IncPD,'Scenario Inputs'!N52)} -> 0.29 | H17: {=IF('Scenario Inputs'!O52="",IncPD,'Scenario Inputs'!O52)} -> 0.29 | I17: {=IF('Scenario Inputs'!P52="",IncPD,'Scenario Inputs'!P52)} -> 0.29 | ... N17: {=IF('Scenario Inputs'!U52="",IncPD,'Scenario Inputs'!U52)} -> 0.29
B19: Rollout year target percentage
B20: 1 | C20: 2 | D20: 3 | E20: 4 | F20: 5 | G20: 6 | H20: 7 | I20: 8 | J20: 9 | K20: 10 | L20: 11 | M20: 12 | N20: 13
A21: Change in probability of diverting to conservative care | B21: =IF('Scenario Inputs'!I61="",IncCCD1,'Scenario Inputs'!I61) -> 0.1 | C21: =IF('Scenario Inputs'!J61="",IncCCD1,'Scenario Inputs'!J61) -> 0.1 | D21: =IF('Scenario Inputs'!K61="",IncCCD1,'Scenario Inputs'!K61) -> 0.1 | E21: =IF('Scenario Inputs'!L61="",IncCCD1,'Scenario Inputs'!L61) -> 0.1 | F21: =IF('Scenario Inputs'!M61="",IncCCD1,'Scenario Inputs'!M61) -> 0.1 | G21: =IF('Scenario Inputs'!N61="",IncCCD1,'Scenario Inputs'!N61) -> 0.1 | H21: =IF('Scenario Inputs'!O61="",IncCCD1,'Scenario Inputs'!O61) -> 0.1 | I21: =IF('Scenario Inputs'!P61="",IncCCD1,'Scenario Inputs'!P61) -> 0.1 | ... N21: =IF('Scenario Inputs'!U61="",IncCCD1,'Scenario Inputs'!U61) -> 0.1
B22: =IF('Scenario Inputs'!I62="",IncCCD2,'Scenario Inputs'!I62) -> 0.1 | C22: =IF('Scenario Inputs'!J62="",IncCCD2,'Scenario Inputs'!J62) -> 0.1 | D22: =IF('Scenario Inputs'!K62="",IncCCD2,'Scenario Inputs'!K62) -> 0.1 | E22: =IF('Scenario Inputs'!L62="",IncCCD2,'Scenario Inputs'!L62) -> 0.1 | F22: =IF('Scenario Inputs'!M62="",IncCCD2,'Scenario Inputs'!M62) -> 0.1 | G22: =IF('Scenario Inputs'!N62="",IncCCD2,'Scenario Inputs'!N62) -> 0.1 | H22: =IF('Scenario Inputs'!O62="",IncCCD2,'Scenario Inputs'!O62) -> 0.1 | I22: =IF('Scenario Inputs'!P62="",IncCCD2,'Scenario Inputs'!P62) -> 0.1 | ... N22: =IF('Scenario Inputs'!U62="",IncCCD2,'Scenario Inputs'!U62) -> 0.1
B23: =IF('Scenario Inputs'!I63="",IncCCD3,'Scenario Inputs'!I63) -> 0.1 | C23: =IF('Scenario Inputs'!J63="",IncCCD3,'Scenario Inputs'!J63) -> 0.1 | D23: =IF('Scenario Inputs'!K63="",IncCCD3,'Scenario Inputs'!K63) -> 0.1 | E23: =IF('Scenario Inputs'!L63="",IncCCD3,'Scenario Inputs'!L63) -> 0.1 | F23: =IF('Scenario Inputs'!M63="",IncCCD3,'Scenario Inputs'!M63) -> 0.1 | G23: =IF('Scenario Inputs'!N63="",IncCCD3,'Scenario Inputs'!N63) -> 0.1 | H23: =IF('Scenario Inputs'!O63="",IncCCD3,'Scenario Inputs'!O63) -> 0.1 | I23: =IF('Scenario Inputs'!P63="",IncCCD3,'Scenario Inputs'!P63) -> 0.1 | ... N23: =IF('Scenario Inputs'!U63="",IncCCD3,'Scenario Inputs'!U63) -> 0.1
B24: =IF('Scenario Inputs'!I64="",IncCCD4,'Scenario Inputs'!I64) -> 0.1 | C24: =IF('Scenario Inputs'!J64="",IncCCD4,'Scenario Inputs'!J64) -> 0.1 | D24: =IF('Scenario Inputs'!K64="",IncCCD4,'Scenario Inputs'!K64) -> 0.1 | E24: =IF('Scenario Inputs'!L64="",IncCCD4,'Scenario Inputs'!L64) -> 0.1 | F24: =IF('Scenario Inputs'!M64="",IncCCD4,'Scenario Inputs'!M64) -> 0.1 | G24: =IF('Scenario Inputs'!N64="",IncCCD4,'Scenario Inputs'!N64) -> 0.1 | H24: =IF('Scenario Inputs'!O64="",IncCCD4,'Scenario Inputs'!O64) -> 0.1 | I24: =IF('Scenario Inputs'!P64="",IncCCD4,'Scenario Inputs'!P64) -> 0.1 | ... N24: =IF('Scenario Inputs'!U64="",IncCCD4,'Scenario Inputs'!U64) -> 0.1
B25: =IF('Scenario Inputs'!I65="",IncCCD5,'Scenario Inputs'!I65) -> 0.25 | C25: =IF('Scenario Inputs'!J65="",IncCCD5,'Scenario Inputs'!J65) -> 0.25 | D25: =IF('Scenario Inputs'!K65="",IncCCD5,'Scenario Inputs'!K65) -> 0.25 | E25: =IF('Scenario Inputs'!L65="",IncCCD5,'Scenario Inputs'!L65) -> 0.25 | F25: =IF('Scenario Inputs'!M65="",IncCCD5,'Scenario Inputs'!M65) -> 0.25 | G25: =IF('Scenario Inputs'!N65="",IncCCD5,'Scenario Inputs'!N65) -> 0.25 | H25: =IF('Scenario Inputs'!O65="",IncCCD5,'Scenario Inputs'!O65) -> 0.25 | I25: =IF('Scenario Inputs'!P65="",IncCCD5,'Scenario Inputs'!P65) -> 0.25 | ... N25: =IF('Scenario Inputs'!U65="",IncCCD5,'Scenario Inputs'!U65) -> 0.25
B26: =IF('Scenario Inputs'!I66="",IncCCD6,'Scenario Inputs'!I66) -> 0.5 | C26: =IF('Scenario Inputs'!J66="",IncCCD6,'Scenario Inputs'!J66) -> 0.5 | D26: =IF('Scenario Inputs'!K66="",IncCCD6,'Scenario Inputs'!K66) -> 0.5 | E26: =IF('Scenario Inputs'!L66="",IncCCD6,'Scenario Inputs'!L66) -> 0.5 | F26: =IF('Scenario Inputs'!M66="",IncCCD6,'Scenario Inputs'!M66) -> 0.5 | G26: =IF('Scenario Inputs'!N66="",IncCCD6,'Scenario Inputs'!N66) -> 0.5 | H26: =IF('Scenario Inputs'!O66="",IncCCD6,'Scenario Inputs'!O66) -> 0.5 | I26: =IF('Scenario Inputs'!P66="",IncCCD6,'Scenario Inputs'!P66) -> 0.5 | ... N26: =IF('Scenario Inputs'!U66="",IncCCD6,'Scenario Inputs'!U66) -> 0.5
A27: Change in probability of late presentation | B27: =IF('Scenario Inputs'!I67="",IncLP,'Scenario Inputs'!I67) -> 0.2 | C27: =IF('Scenario Inputs'!J67="",IncLP,'Scenario Inputs'!J67) -> 0.2 | D27: =IF('Scenario Inputs'!K67="",IncLP,'Scenario Inputs'!K67) -> 0.2 | E27: =IF('Scenario Inputs'!L67="",IncLP,'Scenario Inputs'!L67) -> 0.2 | F27: =IF('Scenario Inputs'!M67="",IncLP,'Scenario Inputs'!M67) -> 0.2 | G27: =IF('Scenario Inputs'!N67="",IncLP,'Scenario Inputs'!N67) -> 0.2 | H27: =IF('Scenario Inputs'!O67="",IncLP,'Scenario Inputs'!O67) -> 0.2 | I27: =IF('Scenario Inputs'!P67="",IncLP,'Scenario Inputs'!P67) -> 0.2 | ... N27: =IF('Scenario Inputs'!U67="",IncLP,'Scenario Inputs'!U67) -> 0.2
C29: Rollout year target
B30: Current Value (Default) | C30: 1 | D30: 2 | E30: 3 | F30: 4 | G30: 5 | H30: 6 | I30: 7 | J30: 8 | K30: 9 | L30: 10 | M30: 11 | N30: 12 | O30: 13
A33: Change in probability of pre-emptive live transplant | B33: =IncPElive -> 0.5 | C33: =IF('Scenario Inputs'!I94="",IncPElive,'Scenario Inputs'!I94) -> 0.5 | D33: =IF('Scenario Inputs'!J94="",IncPElive,'Scenario Inputs'!J94) -> 0.5 | E33: =IF('Scenario Inputs'!K94="",IncPElive,'Scenario Inputs'!K94) -> 0.5 | F33: =IF('Scenario Inputs'!L94="",IncPElive,'Scenario Inputs'!L94) -> 0.5 | G33: =IF('Scenario Inputs'!M94="",IncPElive,'Scenario Inputs'!M94) -> 0.5 | H33: =IF('Scenario Inputs'!N94="",IncPElive,'Scenario Inputs'!N94) -> 0.5 | I33: =IF('Scenario Inputs'!O94="",IncPElive,'Scenario Inputs'!O94) -> 0.5 | J33: =IF('Scenario Inputs'!P94="",IncPElive,'Scenario Inputs'!P94) -> 0.5 | ... O33: =IF('Scenario Inputs'!U94="",IncPElive,'Scenario Inputs'!U94) -> 0.5
A34: Change in probability of pre-emptive cadaver transplant | B34: =IncPEcad -> 0 | C34: =IF('Scenario Inputs'!I97="",IncPEcad,'Scenario Inputs'!I97) -> 0 | D34: =IF('Scenario Inputs'!J97="",IncPEcad,'Scenario Inputs'!J97) -> 0 | E34: =IF('Scenario Inputs'!K97="",IncPEcad,'Scenario Inputs'!K97) -> 0 | F34: =IF('Scenario Inputs'!L97="",IncPEcad,'Scenario Inputs'!L97) -> 0 | G34: =IF('Scenario Inputs'!M97="",IncPEcad,'Scenario Inputs'!M97) -> 0 | H34: =IF('Scenario Inputs'!N97="",IncPEcad,'Scenario Inputs'!N97) -> 0 | I34: =IF('Scenario Inputs'!O97="",IncPEcad,'Scenario Inputs'!O97) -> 0 | J34: =IF('Scenario Inputs'!P97="",IncPEcad,'Scenario Inputs'!P97) -> 0 | ... O34: =IF('Scenario Inputs'!U97="",IncPEcad,'Scenario Inputs'!U97) -> 0
A37: Costs
A38: Daily average cost of ICHD | B38: ='Cost Inputs'!K18/365 -> 172.17
A39: Daily average cost of HHD | B39: ='Cost Inputs'!K19/365 -> 140.06
A40: Daily average cost of PD | B40: ='Cost Inputs'!K20/365 -> 107.92
A41: Daily average cost of Living with Tx | B41: ='Cost Inputs'!K21/365 -> 24.67
A43: Arrival Process | C43: 2010 | D43: 2011 | E43: 2012 | F43: 2013 | G43: 2014 | H43: 2015 | I43: 2016 | J43: 2017 | K43: 2018 | L43: 2019 | M43: 2020 | N43: 2021 | O43: 2022 | P43: 2023 | Q43: 2023 | R43: 2024 | S43: 2025 | T43: 2026 | U43: 2027 | V43: 2028 | W43: 2029 | X43: 2030 | Y43: 2031 | Z43: 2032 | AA43: 2033 | AB43: 2034
C44: =daily_rate!A4 -> 0 | D44: =daily_rate!B4 -> 0 | E44: =daily_rate!C4 -> 0 | F44: =daily_rate!D4 -> 0 | G44: =daily_rate!E4 -> 0 | H44: =daily_rate!F4 -> 0 | I44: =daily_rate!G4 -> 0 | J44: =daily_rate!H4 -> 0 | ... AB44: =daily_rate!Z4 -> 0
C45: Validation | P45: Experimentation
A46: Routing Distributions
A48: Suitable for transplant | B48: Inc | C48: Prev | E48: Receives Tx | F48: Inc | G48: Prev | I48: Initially | J48: 1 | K48: 2 | L48: 3 | M48: 4 | N48: 5 | O48: 6 | P48: 7 | Q48: 8 | R48: 9 | S48: 10 | T48: 11 | U48: 12 | V48: 13
A49: 1 | B49: =suitableForTx!B1 -> 0.7 | C49: =suitableForTx!B9 -> 0.7 | E49: 1 | F49: =receivesTx!B1 -> 0.9 | G49: =receivesTx!B9 -> 0.6 | I49: =F49 -> 0.9 | J49: =IF('Scenario Inputs'!I91="",simPy_sheet!$I49,'Scenario Inputs'!I91) -> 0.9 | K49: =IF('Scenario Inputs'!J91="",simPy_sheet!$I49,'Scenario Inputs'!J91) -> 0.9 | L49: =IF('Scenario Inputs'!K91="",simPy_sheet!$I49,'Scenario Inputs'!K91) -> 0.9 | M49: =IF('Scenario Inputs'!L91="",simPy_sheet!$I49,'Scenario Inputs'!L91) -> 0.9 | N49: =IF('Scenario Inputs'!M91="",simPy_sheet!$I49,'Scenario Inputs'!M91) -> 0.9 | O49: =IF('Scenario Inputs'!N91="",simPy_sheet!$I49,'Scenario Inputs'!N91) -> 0.9 | P49: =IF('Scenario Inputs'!O91="",simPy_sheet!$I49,'Scenario Inputs'!O91) -> 0.9 | Q49: =IF('Scenario Inputs'!P91="",simPy_sheet!$I49,'Scenario Inputs'!P91) -> 0.9 | ... V49: =IF('Scenario Inputs'!U91="",simPy_sheet!$I49,'Scenario Inputs'!U91) -> 0.9
A50: 2 | B50: =suitableForTx!B2 -> 0.6 | C50: =suitableForTx!B10 -> 0.6 | E50: 2 | F50: =receivesTx!B2 -> 0.8 | G50: =receivesTx!B10 -> 0.3 | I50: =F50 -> 0.8 | J50: =IF('Scenario Inputs'!I92="",simPy_sheet!$I50,'Scenario Inputs'!I92) -> 0.8 | K50: =IF('Scenario Inputs'!J92="",simPy_sheet!$I50,'Scenario Inputs'!J92) -> 0.8 | L50: =IF('Scenario Inputs'!K92="",simPy_sheet!$I50,'Scenario Inputs'!K92) -> 0.8 | M50: =IF('Scenario Inputs'!L92="",simPy_sheet!$I50,'Scenario Inputs'!L92) -> 0.8 | N50: =IF('Scenario Inputs'!M92="",simPy_sheet!$I50,'Scenario Inputs'!M92) -> 0.8 | O50: =IF('Scenario Inputs'!N92="",simPy_sheet!$I50,'Scenario Inputs'!N92) -> 0.8 | P50: =IF('Scenario Inputs'!O92="",simPy_sheet!$I50,'Scenario Inputs'!O92) -> 0.8 | Q50: =IF('Scenario Inputs'!P92="",simPy_sheet!$I50,'Scenario Inputs'!P92) -> 0.8 | ... V50: =IF('Scenario Inputs'!U92="",simPy_sheet!$I50,'Scenario Inputs'!U92) -> 0.8
A51: 3 | B51: =suitableForTx!B3 -> 0.5 | C51: =suitableForTx!B11 -> 0.5 | E51: 3 | F51: =receivesTx!B3 -> 0.6 | G51: =receivesTx!B11 -> 0.3 | I51: =F51 -> 0.6 | J51: =IF('Scenario Inputs'!I93="",simPy_sheet!$I51,'Scenario Inputs'!I93) -> 0.6 | K51: =IF('Scenario Inputs'!J93="",simPy_sheet!$I51,'Scenario Inputs'!J93) -> 0.6 | L51: =IF('Scenario Inputs'!K93="",simPy_sheet!$I51,'Scenario Inputs'!K93) -> 0.6 | M51: =IF('Scenario Inputs'!L93="",simPy_sheet!$I51,'Scenario Inputs'!L93) -> 0.6 | N51: =IF('Scenario Inputs'!M93="",simPy_sheet!$I51,'Scenario Inputs'!M93) -> 0.6 | O51: =IF('Scenario Inputs'!N93="",simPy_sheet!$I51,'Scenario Inputs'!N93) -> 0.6 | P51: =IF('Scenario Inputs'!O93="",simPy_sheet!$I51,'Scenario Inputs'!O93) -> 0.6 | Q51: =IF('Scenario Inputs'!P93="",simPy_sheet!$I51,'Scenario Inputs'!P93) -> 0.6 | ... V51: =IF('Scenario Inputs'!U93="",simPy_sheet!$I51,'Scenario Inputs'!U93) -> 0.6
A52: 4 | B52: =suitableForTx!B4 -> 0.4 | C52: =suitableForTx!B12 -> 0.4 | E52: 4 | F52: =receivesTx!B4 -> 0.5 | G52: =receivesTx!B12 -> 0.3 | I52: =F52 -> 0.5 | J52: =IF('Scenario Inputs'!I94="",simPy_sheet!$I52,'Scenario Inputs'!I94) -> 0.5 | K52: =IF('Scenario Inputs'!J94="",simPy_sheet!$I52,'Scenario Inputs'!J94) -> 0.5 | L52: =IF('Scenario Inputs'!K94="",simPy_sheet!$I52,'Scenario Inputs'!K94) -> 0.5 | M52: =IF('Scenario Inputs'!L94="",simPy_sheet!$I52,'Scenario Inputs'!L94) -> 0.5 | N52: =IF('Scenario Inputs'!M94="",simPy_sheet!$I52,'Scenario Inputs'!M94) -> 0.5 | O52: =IF('Scenario Inputs'!N94="",simPy_sheet!$I52,'Scenario Inputs'!N94) -> 0.5 | P52: =IF('Scenario Inputs'!O94="",simPy_sheet!$I52,'Scenario Inputs'!O94) -> 0.5 | Q52: =IF('Scenario Inputs'!P94="",simPy_sheet!$I52,'Scenario Inputs'!P94) -> 0.5 | ... V52: =IF('Scenario Inputs'!U94="",simPy_sheet!$I52,'Scenario Inputs'!U94) -> 0.5
A53: 5 | B53: =suitableForTx!B5 -> 0.2 | C53: =suitableForTx!B13 -> 0.2 | E53: 5 | F53: =receivesTx!B5 -> 0.5 | G53: =receivesTx!B13 -> 0.15 | I53: =F53 -> 0.5 | J53: =IF('Scenario Inputs'!I95="",simPy_sheet!$I53,'Scenario Inputs'!I95) -> 0.5 | K53: =IF('Scenario Inputs'!J95="",simPy_sheet!$I53,'Scenario Inputs'!J95) -> 0.5 | L53: =IF('Scenario Inputs'!K95="",simPy_sheet!$I53,'Scenario Inputs'!K95) -> 0.5 | M53: =IF('Scenario Inputs'!L95="",simPy_sheet!$I53,'Scenario Inputs'!L95) -> 0.5 | N53: =IF('Scenario Inputs'!M95="",simPy_sheet!$I53,'Scenario Inputs'!M95) -> 0.5 | O53: =IF('Scenario Inputs'!N95="",simPy_sheet!$I53,'Scenario Inputs'!N95) -> 0.5 | P53: =IF('Scenario Inputs'!O95="",simPy_sheet!$I53,'Scenario Inputs'!O95) -> 0.5 | Q53: =IF('Scenario Inputs'!P95="",simPy_sheet!$I53,'Scenario Inputs'!P95) -> 0.5 | ... V53: =IF('Scenario Inputs'!U95="",simPy_sheet!$I53,'Scenario Inputs'!U95) -> 0.5
A54: 6 | B54: =suitableForTx!B6 -> 0.05 | C54: =suitableForTx!B14 -> 0.05 | E54: 6 | F54: =receivesTx!B6 -> 0.1 | G54: =receivesTx!B14 -> 0.1 | I54: =F54 -> 0.1 | J54: =IF('Scenario Inputs'!I96="",simPy_sheet!$I54,'Scenario Inputs'!I96) -> 0.1 | K54: =IF('Scenario Inputs'!J96="",simPy_sheet!$I54,'Scenario Inputs'!J96) -> 0.1 | L54: =IF('Scenario Inputs'!K96="",simPy_sheet!$I54,'Scenario Inputs'!K96) -> 0.1 | M54: =IF('Scenario Inputs'!L96="",simPy_sheet!$I54,'Scenario Inputs'!L96) -> 0.1 | N54: =IF('Scenario Inputs'!M96="",simPy_sheet!$I54,'Scenario Inputs'!M96) -> 0.1 | O54: =IF('Scenario Inputs'!N96="",simPy_sheet!$I54,'Scenario Inputs'!N96) -> 0.1 | P54: =IF('Scenario Inputs'!O96="",simPy_sheet!$I54,'Scenario Inputs'!O96) -> 0.1 | Q54: =IF('Scenario Inputs'!P96="",simPy_sheet!$I54,'Scenario Inputs'!P96) -> 0.1 | ... V54: =IF('Scenario Inputs'!U96="",simPy_sheet!$I54,'Scenario Inputs'!U96) -> 0.1
AG55: There is currently no change in pre-emptive by age, the data values got too low in some regions to be able to estimate this well
A56: Pre-emptive cadaver | C56: 1 | D56: 2 | E56: 3 | F56: 4 | G56: 5 | H56: 6 | I56: 7 | J56: 8 | K56: 9 | L56: 10 | M56: 11 | N56: 12 | O56: 13 | Q56: Pre-emptive live | S56: 1 | T56: 2 | U56: 3 | V56: 4 | W56: 5 | X56: 6 | Y56: 7 | Z56: 8 | AA56: 9 | AB56: 10 | AC56: 11 | AD56: 12 | AE56: 13 | AG56: Pre-emptive combined | AI56: Initial | AJ56: 1 | AK56: 2 | AL56: 3 | AM56: 4 | AN56: 5 | AO56: 6 | AP56: 7 | AQ56: 8 | AR56: 9 | AS56: 10 | AT56: 11 | AU56: 12 | AV56: 13
A57: Early | B57: 1 | C57: =IF(AJ57*2*preE_Tx_Live!$C1/SUM(preE_Tx_Cadav!$C1,preE_Tx_Live!$C1)<=1,AJ57*2*preE_Tx_Cadav!$C1/SUM(preE_Tx_Cadav!$C1,preE_Tx_Live!$C1),2*AJ57-1) -> 0.1 | D57: =IF(AK57*2*preE_Tx_Live!$C1/SUM(preE_Tx_Cadav!$C1,preE_Tx_Live!$C1)<=1,AK57*2*preE_Tx_Cadav!$C1/SUM(preE_Tx_Cadav!$C1,preE_Tx_Live!$C1),2*AK57-1) -> 0.1 | E57: =IF(AL57*2*preE_Tx_Live!$C1/SUM(preE_Tx_Cadav!$C1,preE_Tx_Live!$C1)<=1,AL57*2*preE_Tx_Cadav!$C1/SUM(preE_Tx_Cadav!$C1,preE_Tx_Live!$C1),2*AL57-1) -> 0.1 | F57: =IF(AM57*2*preE_Tx_Live!$C1/SUM(preE_Tx_Cadav!$C1,preE_Tx_Live!$C1)<=1,AM57*2*preE_Tx_Cadav!$C1/SUM(preE_Tx_Cadav!$C1,preE_Tx_Live!$C1),2*AM57-1) -> 0.1 | G57: =IF(AN57*2*preE_Tx_Live!$C1/SUM(preE_Tx_Cadav!$C1,preE_Tx_Live!$C1)<=1,AN57*2*preE_Tx_Cadav!$C1/SUM(preE_Tx_Cadav!$C1,preE_Tx_Live!$C1),2*AN57-1) -> 0.1 | H57: =IF(AO57*2*preE_Tx_Live!$C1/SUM(preE_Tx_Cadav!$C1,preE_Tx_Live!$C1)<=1,AO57*2*preE_Tx_Cadav!$C1/SUM(preE_Tx_Cadav!$C1,preE_Tx_Live!$C1),2*AO57-1) -> 0.1 | I57: =IF(AP57*2*preE_Tx_Live!$C1/SUM(preE_Tx_Cadav!$C1,preE_Tx_Live!$C1)<=1,AP57*2*preE_Tx_Cadav!$C1/SUM(preE_Tx_Cadav!$C1,preE_Tx_Live!$C1),2*AP57-1) -> 0.1 | J57: =IF(AQ57*2*preE_Tx_Live!$C1/SUM(preE_Tx_Cadav!$C1,preE_Tx_Live!$C1)<=1,AQ57*2*preE_Tx_Cadav!$C1/SUM(preE_Tx_Cadav!$C1,preE_Tx_Live!$C1),2*AQ57-1) -> 0.1 | ... O57: =IF(AV57*2*preE_Tx_Live!$C1/SUM(preE_Tx_Cadav!$C1,preE_Tx_Live!$C1)<=1,AV57*2*preE_Tx_Cadav!$C1/SUM(preE_Tx_Cadav!$C1,preE_Tx_Live!$C1),2*AV57-1) -> 0.1 | Q57: Early | R57: 1 | S57: =IF(AJ57*2*preE_Tx_Live!$C1/SUM(preE_Tx_Cadav!$C1,preE_Tx_Live!$C1)<=1,AJ57*2*preE_Tx_Live!$C1/SUM(preE_Tx_Cadav!$C1,preE_Tx_Live!$C1),1) -> 0.3 | T57: =IF(AK57*2*preE_Tx_Live!$C1/SUM(preE_Tx_Cadav!$C1,preE_Tx_Live!$C1)<=1,AK57*2*preE_Tx_Live!$C1/SUM(preE_Tx_Cadav!$C1,preE_Tx_Live!$C1),1) -> 0.3 | U57: =IF(AL57*2*preE_Tx_Live!$C1/SUM(preE_Tx_Cadav!$C1,preE_Tx_Live!$C1)<=1,AL57*2*preE_Tx_Live!$C1/SUM(preE_Tx_Cadav!$C1,preE_Tx_Live!$C1),1) -> 0.3 | V57: =IF(AM57*2*preE_Tx_Live!$C1/SUM(preE_Tx_Cadav!$C1,preE_Tx_Live!$C1)<=1,AM57*2*preE_Tx_Live!$C1/SUM(preE_Tx_Cadav!$C1,preE_Tx_Live!$C1),1) -> 0.3 | W57: =IF(AN57*2*preE_Tx_Live!$C1/SUM(preE_Tx_Cadav!$C1,preE_Tx_Live!$C1)<=1,AN57*2*preE_Tx_Live!$C1/SUM(preE_Tx_Cadav!$C1,preE_Tx_Live!$C1),1) -> 0.3 | X57: =IF(AO57*2*preE_Tx_Live!$C1/SUM(preE_Tx_Cadav!$C1,preE_Tx_Live!$C1)<=1,AO57*2*preE_Tx_Live!$C1/SUM(preE_Tx_Cadav!$C1,preE_Tx_Live!$C1),1) -> 0.3 | Y57: =IF(AP57*2*preE_Tx_Live!$C1/SUM(preE_Tx_Cadav!$C1,preE_Tx_Live!$C1)<=1,AP57*2*preE_Tx_Live!$C1/SUM(preE_Tx_Cadav!$C1,preE_Tx_Live!$C1),1) -> 0.3 | Z57: =IF(AQ57*2*preE_Tx_Live!$C1/SUM(preE_Tx_Cadav!$C1,preE_Tx_Live!$C1)<=1,AQ57*2*preE_Tx_Live!$C1/SUM(preE_Tx_Cadav!$C1,preE_Tx_Live!$C1),1) -> 0.3 | ... AE57: =IF(AV57*2*preE_Tx_Live!$C1/SUM(preE_Tx_Cadav!$C1,preE_Tx_Live!$C1)<=1,AV57*2*preE_Tx_Live!$C1/SUM(preE_Tx_Cadav!$C1,preE_Tx_Live!$C1),1) -> 0.3 | AG57: Early | AH57: 1 | AI57: =AVERAGE(preE_Tx_Cadav!C1,preE_Tx_Live!C1) -> 0.2 | AJ57: =IF('Scenario Inputs'!I$99="",simPy_sheet!$AI$57,'Scenario Inputs'!I$99) -> 0.2 | AK57: =IF('Scenario Inputs'!J$99="",simPy_sheet!$AI$57,'Scenario Inputs'!J$99) -> 0.2 | AL57: =IF('Scenario Inputs'!K$99="",simPy_sheet!$AI$57,'Scenario Inputs'!K$99) -> 0.2 | AM57: =IF('Scenario Inputs'!L$99="",simPy_sheet!$AI$57,'Scenario Inputs'!L$99) -> 0.2 | AN57: =IF('Scenario Inputs'!M$99="",simPy_sheet!$AI$57,'Scenario Inputs'!M$99) -> 0.2 | AO57: =IF('Scenario Inputs'!N$99="",simPy_sheet!$AI$57,'Scenario Inputs'!N$99) -> 0.2 | AP57: =IF('Scenario Inputs'!O$99="",simPy_sheet!$AI$57,'Scenario Inputs'!O$99) -> 0.2 | AQ57: =IF('Scenario Inputs'!P$99="",simPy_sheet!$AI$57,'Scenario Inputs'!P$99) -> 0.2 | ... AV57: =IF('Scenario Inputs'!U$99="",simPy_sheet!$AI$57,'Scenario Inputs'!U$99) -> 0.2
A58: Early | B58: 2 | C58: =IF(AJ58*2*preE_Tx_Live!$C2/SUM(preE_Tx_Cadav!$C2,preE_Tx_Live!$C2)<=1,AJ58*2*preE_Tx_Cadav!$C2/SUM(preE_Tx_Cadav!$C2,preE_Tx_Live!$C2),2*AJ58-1) -> 0.1 | D58: =IF(AK58*2*preE_Tx_Live!$C2/SUM(preE_Tx_Cadav!$C2,preE_Tx_Live!$C2)<=1,AK58*2*preE_Tx_Cadav!$C2/SUM(preE_Tx_Cadav!$C2,preE_Tx_Live!$C2),2*AK58-1) -> 0.1 | E58: =IF(AL58*2*preE_Tx_Live!$C2/SUM(preE_Tx_Cadav!$C2,preE_Tx_Live!$C2)<=1,AL58*2*preE_Tx_Cadav!$C2/SUM(preE_Tx_Cadav!$C2,preE_Tx_Live!$C2),2*AL58-1) -> 0.1 | F58: =IF(AM58*2*preE_Tx_Live!$C2/SUM(preE_Tx_Cadav!$C2,preE_Tx_Live!$C2)<=1,AM58*2*preE_Tx_Cadav!$C2/SUM(preE_Tx_Cadav!$C2,preE_Tx_Live!$C2),2*AM58-1) -> 0.1 | G58: =IF(AN58*2*preE_Tx_Live!$C2/SUM(preE_Tx_Cadav!$C2,preE_Tx_Live!$C2)<=1,AN58*2*preE_Tx_Cadav!$C2/SUM(preE_Tx_Cadav!$C2,preE_Tx_Live!$C2),2*AN58-1) -> 0.1 | H58: =IF(AO58*2*preE_Tx_Live!$C2/SUM(preE_Tx_Cadav!$C2,preE_Tx_Live!$C2)<=1,AO58*2*preE_Tx_Cadav!$C2/SUM(preE_Tx_Cadav!$C2,preE_Tx_Live!$C2),2*AO58-1) -> 0.1 | I58: =IF(AP58*2*preE_Tx_Live!$C2/SUM(preE_Tx_Cadav!$C2,preE_Tx_Live!$C2)<=1,AP58*2*preE_Tx_Cadav!$C2/SUM(preE_Tx_Cadav!$C2,preE_Tx_Live!$C2),2*AP58-1) -> 0.1 | J58: =IF(AQ58*2*preE_Tx_Live!$C2/SUM(preE_Tx_Cadav!$C2,preE_Tx_Live!$C2)<=1,AQ58*2*preE_Tx_Cadav!$C2/SUM(preE_Tx_Cadav!$C2,preE_Tx_Live!$C2),2*AQ58-1) -> 0.1 | ... O58: =IF(AV58*2*preE_Tx_Live!$C2/SUM(preE_Tx_Cadav!$C2,preE_Tx_Live!$C2)<=1,AV58*2*preE_Tx_Cadav!$C2/SUM(preE_Tx_Cadav!$C2,preE_Tx_Live!$C2),2*AV58-1) -> 0.1 | Q58: Early | R58: 2 | S58: =IF(AJ58*2*preE_Tx_Live!$C2/SUM(preE_Tx_Cadav!$C2,preE_Tx_Live!$C2)<=1,AJ58*2*preE_Tx_Live!$C2/SUM(preE_Tx_Cadav!$C2,preE_Tx_Live!$C2),1) -> 0.3 | T58: =IF(AK58*2*preE_Tx_Live!$C2/SUM(preE_Tx_Cadav!$C2,preE_Tx_Live!$C2)<=1,AK58*2*preE_Tx_Live!$C2/SUM(preE_Tx_Cadav!$C2,preE_Tx_Live!$C2),1) -> 0.3 | U58: =IF(AL58*2*preE_Tx_Live!$C2/SUM(preE_Tx_Cadav!$C2,preE_Tx_Live!$C2)<=1,AL58*2*preE_Tx_Live!$C2/SUM(preE_Tx_Cadav!$C2,preE_Tx_Live!$C2),1) -> 0.3 | V58: =IF(AM58*2*preE_Tx_Live!$C2/SUM(preE_Tx_Cadav!$C2,preE_Tx_Live!$C2)<=1,AM58*2*preE_Tx_Live!$C2/SUM(preE_Tx_Cadav!$C2,preE_Tx_Live!$C2),1) -> 0.3 | W58: =IF(AN58*2*preE_Tx_Live!$C2/SUM(preE_Tx_Cadav!$C2,preE_Tx_Live!$C2)<=1,AN58*2*preE_Tx_Live!$C2/SUM(preE_Tx_Cadav!$C2,preE_Tx_Live!$C2),1) -> 0.3 | X58: =IF(AO58*2*preE_Tx_Live!$C2/SUM(preE_Tx_Cadav!$C2,preE_Tx_Live!$C2)<=1,AO58*2*preE_Tx_Live!$C2/SUM(preE_Tx_Cadav!$C2,preE_Tx_Live!$C2),1) -> 0.3 | Y58: =IF(AP58*2*preE_Tx_Live!$C2/SUM(preE_Tx_Cadav!$C2,preE_Tx_Live!$C2)<=1,AP58*2*preE_Tx_Live!$C2/SUM(preE_Tx_Cadav!$C2,preE_Tx_Live!$C2),1) -> 0.3 | Z58: =IF(AQ58*2*preE_Tx_Live!$C2/SUM(preE_Tx_Cadav!$C2,preE_Tx_Live!$C2)<=1,AQ58*2*preE_Tx_Live!$C2/SUM(preE_Tx_Cadav!$C2,preE_Tx_Live!$C2),1) -> 0.3 | ... AE58: =IF(AV58*2*preE_Tx_Live!$C2/SUM(preE_Tx_Cadav!$C2,preE_Tx_Live!$C2)<=1,AV58*2*preE_Tx_Live!$C2/SUM(preE_Tx_Cadav!$C2,preE_Tx_Live!$C2),1) -> 0.3 | AG58: Early | AH58: 2 | AI58: =AVERAGE(preE_Tx_Cadav!C2,preE_Tx_Live!C2) -> 0.2 | AJ58: =IF('Scenario Inputs'!I$99="",simPy_sheet!$AI$57,'Scenario Inputs'!I$99) -> 0.2 | AK58: =IF('Scenario Inputs'!J$99="",simPy_sheet!$AI$57,'Scenario Inputs'!J$99) -> 0.2 | AL58: =IF('Scenario Inputs'!K$99="",simPy_sheet!$AI$57,'Scenario Inputs'!K$99) -> 0.2 | AM58: =IF('Scenario Inputs'!L$99="",simPy_sheet!$AI$57,'Scenario Inputs'!L$99) -> 0.2 | AN58: =IF('Scenario Inputs'!M$99="",simPy_sheet!$AI$57,'Scenario Inputs'!M$99) -> 0.2 | AO58: =IF('Scenario Inputs'!N$99="",simPy_sheet!$AI$57,'Scenario Inputs'!N$99) -> 0.2 | AP58: =IF('Scenario Inputs'!O$99="",simPy_sheet!$AI$57,'Scenario Inputs'!O$99) -> 0.2 | AQ58: =IF('Scenario Inputs'!P$99="",simPy_sheet!$AI$57,'Scenario Inputs'!P$99) -> 0.2 | ... AV58: =IF('Scenario Inputs'!U$99="",simPy_sheet!$AI$57,'Scenario Inputs'!U$99) -> 0.2
A59: Early | B59: 3 | C59: =IF(AJ59*2*preE_Tx_Live!$C3/SUM(preE_Tx_Cadav!$C3,preE_Tx_Live!$C3)<=1,AJ59*2*preE_Tx_Cadav!$C3/SUM(preE_Tx_Cadav!$C3,preE_Tx_Live!$C3),2*AJ59-1) -> 0.1 | D59: =IF(AK59*2*preE_Tx_Live!$C3/SUM(preE_Tx_Cadav!$C3,preE_Tx_Live!$C3)<=1,AK59*2*preE_Tx_Cadav!$C3/SUM(preE_Tx_Cadav!$C3,preE_Tx_Live!$C3),2*AK59-1) -> 0.1 | E59: =IF(AL59*2*preE_Tx_Live!$C3/SUM(preE_Tx_Cadav!$C3,preE_Tx_Live!$C3)<=1,AL59*2*preE_Tx_Cadav!$C3/SUM(preE_Tx_Cadav!$C3,preE_Tx_Live!$C3),2*AL59-1) -> 0.1 | F59: =IF(AM59*2*preE_Tx_Live!$C3/SUM(preE_Tx_Cadav!$C3,preE_Tx_Live!$C3)<=1,AM59*2*preE_Tx_Cadav!$C3/SUM(preE_Tx_Cadav!$C3,preE_Tx_Live!$C3),2*AM59-1) -> 0.1 | G59: =IF(AN59*2*preE_Tx_Live!$C3/SUM(preE_Tx_Cadav!$C3,preE_Tx_Live!$C3)<=1,AN59*2*preE_Tx_Cadav!$C3/SUM(preE_Tx_Cadav!$C3,preE_Tx_Live!$C3),2*AN59-1) -> 0.1 | H59: =IF(AO59*2*preE_Tx_Live!$C3/SUM(preE_Tx_Cadav!$C3,preE_Tx_Live!$C3)<=1,AO59*2*preE_Tx_Cadav!$C3/SUM(preE_Tx_Cadav!$C3,preE_Tx_Live!$C3),2*AO59-1) -> 0.1 | I59: =IF(AP59*2*preE_Tx_Live!$C3/SUM(preE_Tx_Cadav!$C3,preE_Tx_Live!$C3)<=1,AP59*2*preE_Tx_Cadav!$C3/SUM(preE_Tx_Cadav!$C3,preE_Tx_Live!$C3),2*AP59-1) -> 0.1 | J59: =IF(AQ59*2*preE_Tx_Live!$C3/SUM(preE_Tx_Cadav!$C3,preE_Tx_Live!$C3)<=1,AQ59*2*preE_Tx_Cadav!$C3/SUM(preE_Tx_Cadav!$C3,preE_Tx_Live!$C3),2*AQ59-1) -> 0.1 | ... O59: =IF(AV59*2*preE_Tx_Live!$C3/SUM(preE_Tx_Cadav!$C3,preE_Tx_Live!$C3)<=1,AV59*2*preE_Tx_Cadav!$C3/SUM(preE_Tx_Cadav!$C3,preE_Tx_Live!$C3),2*AV59-1) -> 0.1 | Q59: Early | R59: 3 | S59: =IF(AJ59*2*preE_Tx_Live!$C3/SUM(preE_Tx_Cadav!$C3,preE_Tx_Live!$C3)<=1,AJ59*2*preE_Tx_Live!$C3/SUM(preE_Tx_Cadav!$C3,preE_Tx_Live!$C3),1) -> 0.3 | T59: =IF(AK59*2*preE_Tx_Live!$C3/SUM(preE_Tx_Cadav!$C3,preE_Tx_Live!$C3)<=1,AK59*2*preE_Tx_Live!$C3/SUM(preE_Tx_Cadav!$C3,preE_Tx_Live!$C3),1) -> 0.3 | U59: =IF(AL59*2*preE_Tx_Live!$C3/SUM(preE_Tx_Cadav!$C3,preE_Tx_Live!$C3)<=1,AL59*2*preE_Tx_Live!$C3/SUM(preE_Tx_Cadav!$C3,preE_Tx_Live!$C3),1) -> 0.3 | V59: =IF(AM59*2*preE_Tx_Live!$C3/SUM(preE_Tx_Cadav!$C3,preE_Tx_Live!$C3)<=1,AM59*2*preE_Tx_Live!$C3/SUM(preE_Tx_Cadav!$C3,preE_Tx_Live!$C3),1) -> 0.3 | W59: =IF(AN59*2*preE_Tx_Live!$C3/SUM(preE_Tx_Cadav!$C3,preE_Tx_Live!$C3)<=1,AN59*2*preE_Tx_Live!$C3/SUM(preE_Tx_Cadav!$C3,preE_Tx_Live!$C3),1) -> 0.3 | X59: =IF(AO59*2*preE_Tx_Live!$C3/SUM(preE_Tx_Cadav!$C3,preE_Tx_Live!$C3)<=1,AO59*2*preE_Tx_Live!$C3/SUM(preE_Tx_Cadav!$C3,preE_Tx_Live!$C3),1) -> 0.3 | Y59: =IF(AP59*2*preE_Tx_Live!$C3/SUM(preE_Tx_Cadav!$C3,preE_Tx_Live!$C3)<=1,AP59*2*preE_Tx_Live!$C3/SUM(preE_Tx_Cadav!$C3,preE_Tx_Live!$C3),1) -> 0.3 | Z59: =IF(AQ59*2*preE_Tx_Live!$C3/SUM(preE_Tx_Cadav!$C3,preE_Tx_Live!$C3)<=1,AQ59*2*preE_Tx_Live!$C3/SUM(preE_Tx_Cadav!$C3,preE_Tx_Live!$C3),1) -> 0.3 | ... AE59: =IF(AV59*2*preE_Tx_Live!$C3/SUM(preE_Tx_Cadav!$C3,preE_Tx_Live!$C3)<=1,AV59*2*preE_Tx_Live!$C3/SUM(preE_Tx_Cadav!$C3,preE_Tx_Live!$C3),1) -> 0.3 | AG59: Early | AH59: 3 | AI59: =AVERAGE(preE_Tx_Cadav!C3,preE_Tx_Live!C3) -> 0.2 | AJ59: =IF('Scenario Inputs'!I$99="",simPy_sheet!$AI$57,'Scenario Inputs'!I$99) -> 0.2 | AK59: =IF('Scenario Inputs'!J$99="",simPy_sheet!$AI$57,'Scenario Inputs'!J$99) -> 0.2 | AL59: =IF('Scenario Inputs'!K$99="",simPy_sheet!$AI$57,'Scenario Inputs'!K$99) -> 0.2 | AM59: =IF('Scenario Inputs'!L$99="",simPy_sheet!$AI$57,'Scenario Inputs'!L$99) -> 0.2 | AN59: =IF('Scenario Inputs'!M$99="",simPy_sheet!$AI$57,'Scenario Inputs'!M$99) -> 0.2 | AO59: =IF('Scenario Inputs'!N$99="",simPy_sheet!$AI$57,'Scenario Inputs'!N$99) -> 0.2 | AP59: =IF('Scenario Inputs'!O$99="",simPy_sheet!$AI$57,'Scenario Inputs'!O$99) -> 0.2 | AQ59: =IF('Scenario Inputs'!P$99="",simPy_sheet!$AI$57,'Scenario Inputs'!P$99) -> 0.2 | ... AV59: =IF('Scenario Inputs'!U$99="",simPy_sheet!$AI$57,'Scenario Inputs'!U$99) -> 0.2
A60: Early | B60: 4 | C60: =IF(AJ60*2*preE_Tx_Live!$C4/SUM(preE_Tx_Cadav!$C4,preE_Tx_Live!$C4)<=1,AJ60*2*preE_Tx_Cadav!$C4/SUM(preE_Tx_Cadav!$C4,preE_Tx_Live!$C4),2*AJ60-1) -> 0.1 | D60: =IF(AK60*2*preE_Tx_Live!$C4/SUM(preE_Tx_Cadav!$C4,preE_Tx_Live!$C4)<=1,AK60*2*preE_Tx_Cadav!$C4/SUM(preE_Tx_Cadav!$C4,preE_Tx_Live!$C4),2*AK60-1) -> 0.1 | E60: =IF(AL60*2*preE_Tx_Live!$C4/SUM(preE_Tx_Cadav!$C4,preE_Tx_Live!$C4)<=1,AL60*2*preE_Tx_Cadav!$C4/SUM(preE_Tx_Cadav!$C4,preE_Tx_Live!$C4),2*AL60-1) -> 0.1 | F60: =IF(AM60*2*preE_Tx_Live!$C4/SUM(preE_Tx_Cadav!$C4,preE_Tx_Live!$C4)<=1,AM60*2*preE_Tx_Cadav!$C4/SUM(preE_Tx_Cadav!$C4,preE_Tx_Live!$C4),2*AM60-1) -> 0.1 | G60: =IF(AN60*2*preE_Tx_Live!$C4/SUM(preE_Tx_Cadav!$C4,preE_Tx_Live!$C4)<=1,AN60*2*preE_Tx_Cadav!$C4/SUM(preE_Tx_Cadav!$C4,preE_Tx_Live!$C4),2*AN60-1) -> 0.1 | H60: =IF(AO60*2*preE_Tx_Live!$C4/SUM(preE_Tx_Cadav!$C4,preE_Tx_Live!$C4)<=1,AO60*2*preE_Tx_Cadav!$C4/SUM(preE_Tx_Cadav!$C4,preE_Tx_Live!$C4),2*AO60-1) -> 0.1 | I60: =IF(AP60*2*preE_Tx_Live!$C4/SUM(preE_Tx_Cadav!$C4,preE_Tx_Live!$C4)<=1,AP60*2*preE_Tx_Cadav!$C4/SUM(preE_Tx_Cadav!$C4,preE_Tx_Live!$C4),2*AP60-1) -> 0.1 | J60: =IF(AQ60*2*preE_Tx_Live!$C4/SUM(preE_Tx_Cadav!$C4,preE_Tx_Live!$C4)<=1,AQ60*2*preE_Tx_Cadav!$C4/SUM(preE_Tx_Cadav!$C4,preE_Tx_Live!$C4),2*AQ60-1) -> 0.1 | ... O60: =IF(AV60*2*preE_Tx_Live!$C4/SUM(preE_Tx_Cadav!$C4,preE_Tx_Live!$C4)<=1,AV60*2*preE_Tx_Cadav!$C4/SUM(preE_Tx_Cadav!$C4,preE_Tx_Live!$C4),2*AV60-1) -> 0.1 | Q60: Early | R60: 4 | S60: =IF(AJ60*2*preE_Tx_Live!$C4/SUM(preE_Tx_Cadav!$C4,preE_Tx_Live!$C4)<=1,AJ60*2*preE_Tx_Live!$C4/SUM(preE_Tx_Cadav!$C4,preE_Tx_Live!$C4),1) -> 0.3 | T60: =IF(AK60*2*preE_Tx_Live!$C4/SUM(preE_Tx_Cadav!$C4,preE_Tx_Live!$C4)<=1,AK60*2*preE_Tx_Live!$C4/SUM(preE_Tx_Cadav!$C4,preE_Tx_Live!$C4),1) -> 0.3 | U60: =IF(AL60*2*preE_Tx_Live!$C4/SUM(preE_Tx_Cadav!$C4,preE_Tx_Live!$C4)<=1,AL60*2*preE_Tx_Live!$C4/SUM(preE_Tx_Cadav!$C4,preE_Tx_Live!$C4),1) -> 0.3 | V60: =IF(AM60*2*preE_Tx_Live!$C4/SUM(preE_Tx_Cadav!$C4,preE_Tx_Live!$C4)<=1,AM60*2*preE_Tx_Live!$C4/SUM(preE_Tx_Cadav!$C4,preE_Tx_Live!$C4),1) -> 0.3 | W60: =IF(AN60*2*preE_Tx_Live!$C4/SUM(preE_Tx_Cadav!$C4,preE_Tx_Live!$C4)<=1,AN60*2*preE_Tx_Live!$C4/SUM(preE_Tx_Cadav!$C4,preE_Tx_Live!$C4),1) -> 0.3 | X60: =IF(AO60*2*preE_Tx_Live!$C4/SUM(preE_Tx_Cadav!$C4,preE_Tx_Live!$C4)<=1,AO60*2*preE_Tx_Live!$C4/SUM(preE_Tx_Cadav!$C4,preE_Tx_Live!$C4),1) -> 0.3 | Y60: =IF(AP60*2*preE_Tx_Live!$C4/SUM(preE_Tx_Cadav!$C4,preE_Tx_Live!$C4)<=1,AP60*2*preE_Tx_Live!$C4/SUM(preE_Tx_Cadav!$C4,preE_Tx_Live!$C4),1) -> 0.3 | Z60: =IF(AQ60*2*preE_Tx_Live!$C4/SUM(preE_Tx_Cadav!$C4,preE_Tx_Live!$C4)<=1,AQ60*2*preE_Tx_Live!$C4/SUM(preE_Tx_Cadav!$C4,preE_Tx_Live!$C4),1) -> 0.3 | ... AE60: =IF(AV60*2*preE_Tx_Live!$C4/SUM(preE_Tx_Cadav!$C4,preE_Tx_Live!$C4)<=1,AV60*2*preE_Tx_Live!$C4/SUM(preE_Tx_Cadav!$C4,preE_Tx_Live!$C4),1) -> 0.3 | AG60: Early | AH60: 4 | AI60: =AVERAGE(preE_Tx_Cadav!C4,preE_Tx_Live!C4) -> 0.2 | AJ60: =IF('Scenario Inputs'!I$99="",simPy_sheet!$AI$57,'Scenario Inputs'!I$99) -> 0.2 | AK60: =IF('Scenario Inputs'!J$99="",simPy_sheet!$AI$57,'Scenario Inputs'!J$99) -> 0.2 | AL60: =IF('Scenario Inputs'!K$99="",simPy_sheet!$AI$57,'Scenario Inputs'!K$99) -> 0.2 | AM60: =IF('Scenario Inputs'!L$99="",simPy_sheet!$AI$57,'Scenario Inputs'!L$99) -> 0.2 | AN60: =IF('Scenario Inputs'!M$99="",simPy_sheet!$AI$57,'Scenario Inputs'!M$99) -> 0.2 | AO60: =IF('Scenario Inputs'!N$99="",simPy_sheet!$AI$57,'Scenario Inputs'!N$99) -> 0.2 | AP60: =IF('Scenario Inputs'!O$99="",simPy_sheet!$AI$57,'Scenario Inputs'!O$99) -> 0.2 | AQ60: =IF('Scenario Inputs'!P$99="",simPy_sheet!$AI$57,'Scenario Inputs'!P$99) -> 0.2 | ... AV60: =IF('Scenario Inputs'!U$99="",simPy_sheet!$AI$57,'Scenario Inputs'!U$99) -> 0.2
A61: Early | B61: 5 | C61: =IF(AJ61*2*preE_Tx_Live!$C5/SUM(preE_Tx_Cadav!$C5,preE_Tx_Live!$C5)<=1,AJ61*2*preE_Tx_Cadav!$C5/SUM(preE_Tx_Cadav!$C5,preE_Tx_Live!$C5),2*AJ61-1) -> 0.1 | D61: =IF(AK61*2*preE_Tx_Live!$C5/SUM(preE_Tx_Cadav!$C5,preE_Tx_Live!$C5)<=1,AK61*2*preE_Tx_Cadav!$C5/SUM(preE_Tx_Cadav!$C5,preE_Tx_Live!$C5),2*AK61-1) -> 0.1 | E61: =IF(AL61*2*preE_Tx_Live!$C5/SUM(preE_Tx_Cadav!$C5,preE_Tx_Live!$C5)<=1,AL61*2*preE_Tx_Cadav!$C5/SUM(preE_Tx_Cadav!$C5,preE_Tx_Live!$C5),2*AL61-1) -> 0.1 | F61: =IF(AM61*2*preE_Tx_Live!$C5/SUM(preE_Tx_Cadav!$C5,preE_Tx_Live!$C5)<=1,AM61*2*preE_Tx_Cadav!$C5/SUM(preE_Tx_Cadav!$C5,preE_Tx_Live!$C5),2*AM61-1) -> 0.1 | G61: =IF(AN61*2*preE_Tx_Live!$C5/SUM(preE_Tx_Cadav!$C5,preE_Tx_Live!$C5)<=1,AN61*2*preE_Tx_Cadav!$C5/SUM(preE_Tx_Cadav!$C5,preE_Tx_Live!$C5),2*AN61-1) -> 0.1 | H61: =IF(AO61*2*preE_Tx_Live!$C5/SUM(preE_Tx_Cadav!$C5,preE_Tx_Live!$C5)<=1,AO61*2*preE_Tx_Cadav!$C5/SUM(preE_Tx_Cadav!$C5,preE_Tx_Live!$C5),2*AO61-1) -> 0.1 | I61: =IF(AP61*2*preE_Tx_Live!$C5/SUM(preE_Tx_Cadav!$C5,preE_Tx_Live!$C5)<=1,AP61*2*preE_Tx_Cadav!$C5/SUM(preE_Tx_Cadav!$C5,preE_Tx_Live!$C5),2*AP61-1) -> 0.1 | J61: =IF(AQ61*2*preE_Tx_Live!$C5/SUM(preE_Tx_Cadav!$C5,preE_Tx_Live!$C5)<=1,AQ61*2*preE_Tx_Cadav!$C5/SUM(preE_Tx_Cadav!$C5,preE_Tx_Live!$C5),2*AQ61-1) -> 0.1 | ... O61: =IF(AV61*2*preE_Tx_Live!$C5/SUM(preE_Tx_Cadav!$C5,preE_Tx_Live!$C5)<=1,AV61*2*preE_Tx_Cadav!$C5/SUM(preE_Tx_Cadav!$C5,preE_Tx_Live!$C5),2*AV61-1) -> 0.1 | Q61: Early | R61: 5 | S61: =IF(AJ61*2*preE_Tx_Live!$C5/SUM(preE_Tx_Cadav!$C5,preE_Tx_Live!$C5)<=1,AJ61*2*preE_Tx_Live!$C5/SUM(preE_Tx_Cadav!$C5,preE_Tx_Live!$C5),1) -> 0.3 | T61: =IF(AK61*2*preE_Tx_Live!$C5/SUM(preE_Tx_Cadav!$C5,preE_Tx_Live!$C5)<=1,AK61*2*preE_Tx_Live!$C5/SUM(preE_Tx_Cadav!$C5,preE_Tx_Live!$C5),1) -> 0.3 | U61: =IF(AL61*2*preE_Tx_Live!$C5/SUM(preE_Tx_Cadav!$C5,preE_Tx_Live!$C5)<=1,AL61*2*preE_Tx_Live!$C5/SUM(preE_Tx_Cadav!$C5,preE_Tx_Live!$C5),1) -> 0.3 | V61: =IF(AM61*2*preE_Tx_Live!$C5/SUM(preE_Tx_Cadav!$C5,preE_Tx_Live!$C5)<=1,AM61*2*preE_Tx_Live!$C5/SUM(preE_Tx_Cadav!$C5,preE_Tx_Live!$C5),1) -> 0.3 | W61: =IF(AN61*2*preE_Tx_Live!$C5/SUM(preE_Tx_Cadav!$C5,preE_Tx_Live!$C5)<=1,AN61*2*preE_Tx_Live!$C5/SUM(preE_Tx_Cadav!$C5,preE_Tx_Live!$C5),1) -> 0.3 | X61: =IF(AO61*2*preE_Tx_Live!$C5/SUM(preE_Tx_Cadav!$C5,preE_Tx_Live!$C5)<=1,AO61*2*preE_Tx_Live!$C5/SUM(preE_Tx_Cadav!$C5,preE_Tx_Live!$C5),1) -> 0.3 | Y61: =IF(AP61*2*preE_Tx_Live!$C5/SUM(preE_Tx_Cadav!$C5,preE_Tx_Live!$C5)<=1,AP61*2*preE_Tx_Live!$C5/SUM(preE_Tx_Cadav!$C5,preE_Tx_Live!$C5),1) -> 0.3 | Z61: =IF(AQ61*2*preE_Tx_Live!$C5/SUM(preE_Tx_Cadav!$C5,preE_Tx_Live!$C5)<=1,AQ61*2*preE_Tx_Live!$C5/SUM(preE_Tx_Cadav!$C5,preE_Tx_Live!$C5),1) -> 0.3 | ... AE61: =IF(AV61*2*preE_Tx_Live!$C5/SUM(preE_Tx_Cadav!$C5,preE_Tx_Live!$C5)<=1,AV61*2*preE_Tx_Live!$C5/SUM(preE_Tx_Cadav!$C5,preE_Tx_Live!$C5),1) -> 0.3 | AG61: Early | AH61: 5 | AI61: =AVERAGE(preE_Tx_Cadav!C5,preE_Tx_Live!C5) -> 0.2 | AJ61: =IF('Scenario Inputs'!I$99="",simPy_sheet!$AI$57,'Scenario Inputs'!I$99) -> 0.2 | AK61: =IF('Scenario Inputs'!J$99="",simPy_sheet!$AI$57,'Scenario Inputs'!J$99) -> 0.2 | AL61: =IF('Scenario Inputs'!K$99="",simPy_sheet!$AI$57,'Scenario Inputs'!K$99) -> 0.2 | AM61: =IF('Scenario Inputs'!L$99="",simPy_sheet!$AI$57,'Scenario Inputs'!L$99) -> 0.2 | AN61: =IF('Scenario Inputs'!M$99="",simPy_sheet!$AI$57,'Scenario Inputs'!M$99) -> 0.2 | AO61: =IF('Scenario Inputs'!N$99="",simPy_sheet!$AI$57,'Scenario Inputs'!N$99) -> 0.2 | AP61: =IF('Scenario Inputs'!O$99="",simPy_sheet!$AI$57,'Scenario Inputs'!O$99) -> 0.2 | AQ61: =IF('Scenario Inputs'!P$99="",simPy_sheet!$AI$57,'Scenario Inputs'!P$99) -> 0.2 | ... AV61: =IF('Scenario Inputs'!U$99="",simPy_sheet!$AI$57,'Scenario Inputs'!U$99) -> 0.2
A62: Early | B62: 6 | C62: =IF(AJ62*2*preE_Tx_Live!$C6/SUM(preE_Tx_Cadav!$C6,preE_Tx_Live!$C6)<=1,AJ62*2*preE_Tx_Cadav!$C6/SUM(preE_Tx_Cadav!$C6,preE_Tx_Live!$C6),2*AJ62-1) -> 0.1 | D62: =IF(AK62*2*preE_Tx_Live!$C6/SUM(preE_Tx_Cadav!$C6,preE_Tx_Live!$C6)<=1,AK62*2*preE_Tx_Cadav!$C6/SUM(preE_Tx_Cadav!$C6,preE_Tx_Live!$C6),2*AK62-1) -> 0.1 | E62: =IF(AL62*2*preE_Tx_Live!$C6/SUM(preE_Tx_Cadav!$C6,preE_Tx_Live!$C6)<=1,AL62*2*preE_Tx_Cadav!$C6/SUM(preE_Tx_Cadav!$C6,preE_Tx_Live!$C6),2*AL62-1) -> 0.1 | F62: =IF(AM62*2*preE_Tx_Live!$C6/SUM(preE_Tx_Cadav!$C6,preE_Tx_Live!$C6)<=1,AM62*2*preE_Tx_Cadav!$C6/SUM(preE_Tx_Cadav!$C6,preE_Tx_Live!$C6),2*AM62-1) -> 0.1 | G62: =IF(AN62*2*preE_Tx_Live!$C6/SUM(preE_Tx_Cadav!$C6,preE_Tx_Live!$C6)<=1,AN62*2*preE_Tx_Cadav!$C6/SUM(preE_Tx_Cadav!$C6,preE_Tx_Live!$C6),2*AN62-1) -> 0.1 | H62: =IF(AO62*2*preE_Tx_Live!$C6/SUM(preE_Tx_Cadav!$C6,preE_Tx_Live!$C6)<=1,AO62*2*preE_Tx_Cadav!$C6/SUM(preE_Tx_Cadav!$C6,preE_Tx_Live!$C6),2*AO62-1) -> 0.1 | I62: =IF(AP62*2*preE_Tx_Live!$C6/SUM(preE_Tx_Cadav!$C6,preE_Tx_Live!$C6)<=1,AP62*2*preE_Tx_Cadav!$C6/SUM(preE_Tx_Cadav!$C6,preE_Tx_Live!$C6),2*AP62-1) -> 0.1 | J62: =IF(AQ62*2*preE_Tx_Live!$C6/SUM(preE_Tx_Cadav!$C6,preE_Tx_Live!$C6)<=1,AQ62*2*preE_Tx_Cadav!$C6/SUM(preE_Tx_Cadav!$C6,preE_Tx_Live!$C6),2*AQ62-1) -> 0.1 | ... O62: =IF(AV62*2*preE_Tx_Live!$C6/SUM(preE_Tx_Cadav!$C6,preE_Tx_Live!$C6)<=1,AV62*2*preE_Tx_Cadav!$C6/SUM(preE_Tx_Cadav!$C6,preE_Tx_Live!$C6),2*AV62-1) -> 0.1 | Q62: Early | R62: 6 | S62: =IF(AJ62*2*preE_Tx_Live!$C6/SUM(preE_Tx_Cadav!$C6,preE_Tx_Live!$C6)<=1,AJ62*2*preE_Tx_Live!$C6/SUM(preE_Tx_Cadav!$C6,preE_Tx_Live!$C6),1) -> 0.3 | T62: =IF(AK62*2*preE_Tx_Live!$C6/SUM(preE_Tx_Cadav!$C6,preE_Tx_Live!$C6)<=1,AK62*2*preE_Tx_Live!$C6/SUM(preE_Tx_Cadav!$C6,preE_Tx_Live!$C6),1) -> 0.3 | U62: =IF(AL62*2*preE_Tx_Live!$C6/SUM(preE_Tx_Cadav!$C6,preE_Tx_Live!$C6)<=1,AL62*2*preE_Tx_Live!$C6/SUM(preE_Tx_Cadav!$C6,preE_Tx_Live!$C6),1) -> 0.3 | V62: =IF(AM62*2*preE_Tx_Live!$C6/SUM(preE_Tx_Cadav!$C6,preE_Tx_Live!$C6)<=1,AM62*2*preE_Tx_Live!$C6/SUM(preE_Tx_Cadav!$C6,preE_Tx_Live!$C6),1) -> 0.3 | W62: =IF(AN62*2*preE_Tx_Live!$C6/SUM(preE_Tx_Cadav!$C6,preE_Tx_Live!$C6)<=1,AN62*2*preE_Tx_Live!$C6/SUM(preE_Tx_Cadav!$C6,preE_Tx_Live!$C6),1) -> 0.3 | X62: =IF(AO62*2*preE_Tx_Live!$C6/SUM(preE_Tx_Cadav!$C6,preE_Tx_Live!$C6)<=1,AO62*2*preE_Tx_Live!$C6/SUM(preE_Tx_Cadav!$C6,preE_Tx_Live!$C6),1) -> 0.3 | Y62: =IF(AP62*2*preE_Tx_Live!$C6/SUM(preE_Tx_Cadav!$C6,preE_Tx_Live!$C6)<=1,AP62*2*preE_Tx_Live!$C6/SUM(preE_Tx_Cadav!$C6,preE_Tx_Live!$C6),1) -> 0.3 | Z62: =IF(AQ62*2*preE_Tx_Live!$C6/SUM(preE_Tx_Cadav!$C6,preE_Tx_Live!$C6)<=1,AQ62*2*preE_Tx_Live!$C6/SUM(preE_Tx_Cadav!$C6,preE_Tx_Live!$C6),1) -> 0.3 | ... AE62: =IF(AV62*2*preE_Tx_Live!$C6/SUM(preE_Tx_Cadav!$C6,preE_Tx_Live!$C6)<=1,AV62*2*preE_Tx_Live!$C6/SUM(preE_Tx_Cadav!$C6,preE_Tx_Live!$C6),1) -> 0.3 | AG62: Early | AH62: 6 | AI62: =AVERAGE(preE_Tx_Cadav!C6,preE_Tx_Live!C6) -> 0.2 | AJ62: =IF('Scenario Inputs'!I$99="",simPy_sheet!$AI$57,'Scenario Inputs'!I$99) -> 0.2 | AK62: =IF('Scenario Inputs'!J$99="",simPy_sheet!$AI$57,'Scenario Inputs'!J$99) -> 0.2 | AL62: =IF('Scenario Inputs'!K$99="",simPy_sheet!$AI$57,'Scenario Inputs'!K$99) -> 0.2 | AM62: =IF('Scenario Inputs'!L$99="",simPy_sheet!$AI$57,'Scenario Inputs'!L$99) -> 0.2 | AN62: =IF('Scenario Inputs'!M$99="",simPy_sheet!$AI$57,'Scenario Inputs'!M$99) -> 0.2 | AO62: =IF('Scenario Inputs'!N$99="",simPy_sheet!$AI$57,'Scenario Inputs'!N$99) -> 0.2 | AP62: =IF('Scenario Inputs'!O$99="",simPy_sheet!$AI$57,'Scenario Inputs'!O$99) -> 0.2 | AQ62: =IF('Scenario Inputs'!P$99="",simPy_sheet!$AI$57,'Scenario Inputs'!P$99) -> 0.2 | ... AV62: =IF('Scenario Inputs'!U$99="",simPy_sheet!$AI$57,'Scenario Inputs'!U$99) -> 0.2
A63: Late | B63: 1 | C63: =preE_Tx_Cadav!C7 -> 0 | Q63: Late | R63: 1 | S63: =preE_Tx_Live!C7 -> 0
A64: Late | B64: 2 | C64: =preE_Tx_Cadav!C8 -> 0 | Q64: Late | R64: 2 | S64: =preE_Tx_Live!C8 -> 0
A65: Late | B65: 3 | C65: =preE_Tx_Cadav!C9 -> 0 | Q65: Late | R65: 3 | S65: =preE_Tx_Live!C9 -> 0
A66: Late | B66: 4 | C66: =preE_Tx_Cadav!C10 -> 0 | Q66: Late | R66: 4 | S66: =preE_Tx_Live!C10 -> 0
A67: Late | B67: 5 | C67: =preE_Tx_Cadav!C11 -> 0 | Q67: Late | R67: 5 | S67: =preE_Tx_Live!C11 -> 0
A68: Late | B68: 6 | C68: =preE_Tx_Cadav!C12 -> 0 | Q68: Late | R68: 6 | S68: =preE_Tx_Live!C12 -> 0
A69: Modality allocation | B69: Initially | F69: 1 | I69: 2 | L69: 3 | O69: 4 | R69: 5 | U69: 6 | X69: 7 | AA69: 8 | AD69: 9 | AG69: 10 | AJ69: 11 | AM69: 12 | AP69: 13
C70: ichd | D70: hhd | E70: pd | F70: ichd | G70: hhd | H70: pd | I70: ichd | J70: hhd | K70: pd | L70: ichd | M70: hhd | N70: pd | O70: ichd | P70: hhd | Q70: pd | R70: ichd | S70: hhd | T70: pd | U70: ichd | V70: hhd | W70: pd | X70: ichd | Y70: hhd | Z70: pd | AA70: ichd | AB70: hhd | AC70: pd | AD70: ichd | AE70: hhd | AF70: pd | AG70: ichd | AH70: hhd | AI70: pd | AJ70: ichd | AK70: hhd | AL70: pd | AM70: ichd | AN70: hhd | AO70: pd | AP70: ichd | AQ70: hhd | AR70: pd
A71: "none" | B71: 1 | C71: =modAllocation!C1 -> 0.69 | D71: =modAllocation!D1 -> 0.02 | E71: =modAllocation!E1 -> 0.29 | F71: =1-SUM(G71:H71) -> 0.69 | G71: =D71 -> 0.02 | H71: =$B$17 -> 0.29 | I71: =1-SUM(J71:K71) -> 0.69 | J71: =D71 -> 0.02 | K71: =$C$17 -> 0.29 | L71: =1-SUM(M71:N71) -> 0.69 | M71: =D71 -> 0.02 | N71: =$D$17 -> 0.29 | O71: =1-SUM(P71:Q71) -> 0.69 | P71: =D71 -> 0.02 | Q71: =$E$17 -> 0.29 | R71: =1-SUM(S71:T71) -> 0.69 | S71: =D71 -> 0.02 | T71: =$F$17 -> 0.29 | U71: =1-SUM(V71:W71) -> 0.69 | V71: =D71 -> 0.02 | W71: =$G$17 -> 0.29 | X71: =1-SUM(Y71:Z71) -> 0.69 | Y71: =D71 -> 0.02 | Z71: =$H$17 -> 0.29 | AA71: =1-SUM(AB71:AC71) -> 0.69 | AB71: =D71 -> 0.02 | AC71: =$I$17 -> 0.29 | AD71: =1-SUM(AE71:AF71) -> 0.69 | AE71: =D71 -> 0.02 | AF71: =$J$17 -> 0.29 | AG71: =1-SUM(AH71:AI71) -> 0.69 | AH71: =D71 -> 0.02 | AI71: =$K$17 -> 0.29 | AJ71: =1-SUM(AK71:AL71) -> 0.69 | AK71: =D71 -> 0.02 | AL71: =$L$17 -> 0.29 | AM71: =1-SUM(AN71:AO71) -> 0.69 | AN71: =D71 -> 0.02 | AO71: =$M$17 -> 0.29 | AP71: =1-SUM(AQ71:AR71) -> 0.69 | AQ71: =D71 -> 0.02 | AR71: =$N$17 -> 0.29
A72: "none" | B72: 2 | C72: =modAllocation!C2 -> 0.69 | D72: =modAllocation!D2 -> 0.02 | E72: =modAllocation!E2 -> 0.29 | F72: =1-SUM(G72:H72) -> 0.69 | G72: =D72 -> 0.02 | H72: =$B$17 -> 0.29 | I72: =1-SUM(J72:K72) -> 0.69 | J72: =D72 -> 0.02 | K72: =$C$17 -> 0.29 | L72: =1-SUM(M72:N72) -> 0.69 | M72: =D72 -> 0.02 | N72: =$D$17 -> 0.29 | O72: =1-SUM(P72:Q72) -> 0.69 | P72: =D72 -> 0.02 | Q72: =$E$17 -> 0.29 | R72: =1-SUM(S72:T72) -> 0.69 | S72: =D72 -> 0.02 | T72: =$F$17 -> 0.29 | U72: =1-SUM(V72:W72) -> 0.69 | V72: =D72 -> 0.02 | W72: =$G$17 -> 0.29 | X72: =1-SUM(Y72:Z72) -> 0.69 | Y72: =D72 -> 0.02 | Z72: =$H$17 -> 0.29 | AA72: =1-SUM(AB72:AC72) -> 0.69 | AB72: =D72 -> 0.02 | AC72: =$I$17 -> 0.29 | AD72: =1-SUM(AE72:AF72) -> 0.69 | AE72: =D72 -> 0.02 | AF72: =$J$17 -> 0.29 | AG72: =1-SUM(AH72:AI72) -> 0.69 | AH72: =D72 -> 0.02 | AI72: =$K$17 -> 0.29 | AJ72: =1-SUM(AK72:AL72) -> 0.69 | AK72: =D72 -> 0.02 | AL72: =$L$17 -> 0.29 | AM72: =1-SUM(AN72:AO72) -> 0.69 | AN72: =D72 -> 0.02 | AO72: =$M$17 -> 0.29 | AP72: =1-SUM(AQ72:AR72) -> 0.69 | AQ72: =D72 -> 0.02 | AR72: =$N$17 -> 0.29
A73: "none" | B73: 3 | C73: =modAllocation!C3 -> 0.69 | D73: =modAllocation!D3 -> 0.02 | E73: =modAllocation!E3 -> 0.29 | F73: =1-SUM(G73:H73) -> 0.69 | G73: =D73 -> 0.02 | H73: =$B$17 -> 0.29 | I73: =1-SUM(J73:K73) -> 0.69 | J73: =D73 -> 0.02 | K73: =$C$17 -> 0.29 | L73: =1-SUM(M73:N73) -> 0.69 | M73: =D73 -> 0.02 | N73: =$D$17 -> 0.29 | O73: =1-SUM(P73:Q73) -> 0.69 | P73: =D73 -> 0.02 | Q73: =$E$17 -> 0.29 | R73: =1-SUM(S73:T73) -> 0.69 | S73: =D73 -> 0.02 | T73: =$F$17 -> 0.29 | U73: =1-SUM(V73:W73) -> 0.69 | V73: =D73 -> 0.02 | W73: =$G$17 -> 0.29 | X73: =1-SUM(Y73:Z73) -> 0.69 | Y73: =D73 -> 0.02 | Z73: =$H$17 -> 0.29 | AA73: =1-SUM(AB73:AC73) -> 0.69 | AB73: =D73 -> 0.02 | AC73: =$I$17 -> 0.29 | AD73: =1-SUM(AE73:AF73) -> 0.69 | AE73: =D73 -> 0.02 | AF73: =$J$17 -> 0.29 | AG73: =1-SUM(AH73:AI73) -> 0.69 | AH73: =D73 -> 0.02 | AI73: =$K$17 -> 0.29 | AJ73: =1-SUM(AK73:AL73) -> 0.69 | AK73: =D73 -> 0.02 | AL73: =$L$17 -> 0.29 | AM73: =1-SUM(AN73:AO73) -> 0.69 | AN73: =D73 -> 0.02 | AO73: =$M$17 -> 0.29 | AP73: =1-SUM(AQ73:AR73) -> 0.69 | AQ73: =D73 -> 0.02 | AR73: =$N$17 -> 0.29
A74: "none" | B74: 4 | C74: =modAllocation!C4 -> 0.69 | D74: =modAllocation!D4 -> 0.02 | E74: =modAllocation!E4 -> 0.29 | F74: =1-SUM(G74:H74) -> 0.69 | G74: =D74 -> 0.02 | H74: =$B$17 -> 0.29 | I74: =1-SUM(J74:K74) -> 0.69 | J74: =D74 -> 0.02 | K74: =$C$17 -> 0.29 | L74: =1-SUM(M74:N74) -> 0.69 | M74: =D74 -> 0.02 | N74: =$D$17 -> 0.29 | O74: =1-SUM(P74:Q74) -> 0.69 | P74: =D74 -> 0.02 | Q74: =$E$17 -> 0.29 | R74: =1-SUM(S74:T74) -> 0.69 | S74: =D74 -> 0.02 | T74: =$F$17 -> 0.29 | U74: =1-SUM(V74:W74) -> 0.69 | V74: =D74 -> 0.02 | W74: =$G$17 -> 0.29 | X74: =1-SUM(Y74:Z74) -> 0.69 | Y74: =D74 -> 0.02 | Z74: =$H$17 -> 0.29 | AA74: =1-SUM(AB74:AC74) -> 0.69 | AB74: =D74 -> 0.02 | AC74: =$I$17 -> 0.29 | AD74: =1-SUM(AE74:AF74) -> 0.69 | AE74: =D74 -> 0.02 | AF74: =$J$17 -> 0.29 | AG74: =1-SUM(AH74:AI74) -> 0.69 | AH74: =D74 -> 0.02 | AI74: =$K$17 -> 0.29 | AJ74: =1-SUM(AK74:AL74) -> 0.69 | AK74: =D74 -> 0.02 | AL74: =$L$17 -> 0.29 | AM74: =1-SUM(AN74:AO74) -> 0.69 | AN74: =D74 -> 0.02 | AO74: =$M$17 -> 0.29 | AP74: =1-SUM(AQ74:AR74) -> 0.69 | AQ74: =D74 -> 0.02 | AR74: =$N$17 -> 0.29
A75: "none" | B75: 5 | C75: =modAllocation!C5 -> 0.69 | D75: =modAllocation!D5 -> 0.02 | E75: =modAllocation!E5 -> 0.29 | F75: =1-SUM(G75:H75) -> 0.69 | G75: =D75 -> 0.02 | H75: =$B$17 -> 0.29 | I75: =1-SUM(J75:K75) -> 0.69 | J75: =D75 -> 0.02 | K75: =$C$17 -> 0.29 | L75: =1-SUM(M75:N75) -> 0.69 | M75: =D75 -> 0.02 | N75: =$D$17 -> 0.29 | O75: =1-SUM(P75:Q75) -> 0.69 | P75: =D75 -> 0.02 | Q75: =$E$17 -> 0.29 | R75: =1-SUM(S75:T75) -> 0.69 | S75: =D75 -> 0.02 | T75: =$F$17 -> 0.29 | U75: =1-SUM(V75:W75) -> 0.69 | V75: =D75 -> 0.02 | W75: =$G$17 -> 0.29 | X75: =1-SUM(Y75:Z75) -> 0.69 | Y75: =D75 -> 0.02 | Z75: =$H$17 -> 0.29 | AA75: =1-SUM(AB75:AC75) -> 0.69 | AB75: =D75 -> 0.02 | AC75: =$I$17 -> 0.29 | AD75: =1-SUM(AE75:AF75) -> 0.69 | AE75: =D75 -> 0.02 | AF75: =$J$17 -> 0.29 | AG75: =1-SUM(AH75:AI75) -> 0.69 | AH75: =D75 -> 0.02 | AI75: =$K$17 -> 0.29 | AJ75: =1-SUM(AK75:AL75) -> 0.69 | AK75: =D75 -> 0.02 | AL75: =$L$17 -> 0.29 | AM75: =1-SUM(AN75:AO75) -> 0.69 | AN75: =D75 -> 0.02 | AO75: =$M$17 -> 0.29 | AP75: =1-SUM(AQ75:AR75) -> 0.69 | AQ75: =D75 -> 0.02 | AR75: =$N$17 -> 0.29
A76: "none" | B76: 6 | C76: =modAllocation!C6 -> 0.69 | D76: =modAllocation!D6 -> 0.02 | E76: =modAllocation!E6 -> 0.29 | F76: =1-SUM(G76:H76) -> 0.69 | G76: =D76 -> 0.02 | H76: =$B$17 -> 0.29 | I76: =1-SUM(J76:K76) -> 0.69 | J76: =D76 -> 0.02 | K76: =$C$17 -> 0.29 | L76: =1-SUM(M76:N76) -> 0.69 | M76: =D76 -> 0.02 | N76: =$D$17 -> 0.29 | O76: =1-SUM(P76:Q76) -> 0.69 | P76: =D76 -> 0.02 | Q76: =$E$17 -> 0.29 | R76: =1-SUM(S76:T76) -> 0.69 | S76: =D76 -> 0.02 | T76: =$F$17 -> 0.29 | U76: =1-SUM(V76:W76) -> 0.69 | V76: =D76 -> 0.02 | W76: =$G$17 -> 0.29 | X76: =1-SUM(Y76:Z76) -> 0.69 | Y76: =D76 -> 0.02 | Z76: =$H$17 -> 0.29 | AA76: =1-SUM(AB76:AC76) -> 0.69 | AB76: =D76 -> 0.02 | AC76: =$I$17 -> 0.29 | AD76: =1-SUM(AE76:AF76) -> 0.69 | AE76: =D76 -> 0.02 | AF76: =$J$17 -> 0.29 | AG76: =1-SUM(AH76:AI76) -> 0.69 | AH76: =D76 -> 0.02 | AI76: =$K$17 -> 0.29 | AJ76: =1-SUM(AK76:AL76) -> 0.69 | AK76: =D76 -> 0.02 | AL76: =$L$17 -> 0.29 | AM76: =1-SUM(AN76:AO76) -> 0.69 | AN76: =D76 -> 0.02 | AO76: =$M$17 -> 0.29 | AP76: =1-SUM(AQ76:AR76) -> 0.69 | AQ76: =D76 -> 0.02 | AR76: =$N$17 -> 0.29
A77: "ichd" | B77: 1 | C77: =modAllocation!C7 -> 0 | D77: =modAllocation!D7 -> 0.2 | E77: =modAllocation!E7 -> 0.8 | F77: 0 | G77: =$B$16 -> 0.18918919 | H77: =1-G77 -> 0.81081081 | I77: 0 | J77: =$C$16 -> 0.18918919 | K77: =1-J77 -> 0.81081081 | L77: 0 | M77: =$D$16 -> 0.18918919 | N77: =1-M77 -> 0.81081081 | O77: 0 | P77: =$E$16 -> 0.18918919 | Q77: =1-P77 -> 0.81081081 | R77: 0 | S77: =$F$16 -> 0.18918919 | T77: =1-S77 -> 0.81081081 | U77: 0 | V77: =$G$16 -> 0.18918919 | W77: =1-V77 -> 0.81081081 | X77: 0 | Y77: =$H$16 -> 0.18918919 | Z77: =1-Y77 -> 0.81081081 | AA77: 0 | AB77: =$I$16 -> 0.18918919 | AC77: =1-AB77 -> 0.81081081 | AD77: 0 | AE77: =$J$16 -> 0.18918919 | AF77: =1-AE77 -> 0.81081081 | AG77: 0 | AH77: =$K$16 -> 0.18918919 | AI77: =1-AH77 -> 0.81081081 | AJ77: 0 | AK77: =$L$16 -> 0.18918919 | AL77: =1-AK77 -> 0.81081081 | AM77: 0 | AN77: =$M$16 -> 0.18918919 | AO77: =1-AN77 -> 0.81081081 | AP77: 0 | AQ77: =$N$16 -> 0.18918919 | AR77: =1-AQ77 -> 0.81081081
A78: "ichd" | B78: 2 | C78: =modAllocation!C8 -> 0 | D78: =modAllocation!D8 -> 0.2 | E78: =modAllocation!E8 -> 0.8 | F78: 0 | G78: =$B$16 -> 0.18918919 | H78: =1-G78 -> 0.81081081 | I78: 0 | J78: =$C$16 -> 0.18918919 | K78: =1-J78 -> 0.81081081 | L78: 0 | M78: =$D$16 -> 0.18918919 | N78: =1-M78 -> 0.81081081 | O78: 0 | P78: =$E$16 -> 0.18918919 | Q78: =1-P78 -> 0.81081081 | R78: 0 | S78: =$F$16 -> 0.18918919 | T78: =1-S78 -> 0.81081081 | U78: 0 | V78: =$G$16 -> 0.18918919 | W78: =1-V78 -> 0.81081081 | X78: 0 | Y78: =$H$16 -> 0.18918919 | Z78: =1-Y78 -> 0.81081081 | AA78: 0 | AB78: =$I$16 -> 0.18918919 | AC78: =1-AB78 -> 0.81081081 | AD78: 0 | AE78: =$J$16 -> 0.18918919 | AF78: =1-AE78 -> 0.81081081 | AG78: 0 | AH78: =$K$16 -> 0.18918919 | AI78: =1-AH78 -> 0.81081081 | AJ78: 0 | AK78: =$L$16 -> 0.18918919 | AL78: =1-AK78 -> 0.81081081 | AM78: 0 | AN78: =$M$16 -> 0.18918919 | AO78: =1-AN78 -> 0.81081081 | AP78: 0 | AQ78: =$N$16 -> 0.18918919 | AR78: =1-AQ78 -> 0.81081081
A79: "ichd" | B79: 3 | C79: =modAllocation!C9 -> 0 | D79: =modAllocation!D9 -> 0.2 | E79: =modAllocation!E9 -> 0.8 | F79: 0 | G79: =$B$16 -> 0.18918919 | H79: =1-G79 -> 0.81081081 | I79: 0 | J79: =$C$16 -> 0.18918919 | K79: =1-J79 -> 0.81081081 | L79: 0 | M79: =$D$16 -> 0.18918919 | N79: =1-M79 -> 0.81081081 | O79: 0 | P79: =$E$16 -> 0.18918919 | Q79: =1-P79 -> 0.81081081 | R79: 0 | S79: =$F$16 -> 0.18918919 | T79: =1-S79 -> 0.81081081 | U79: 0 | V79: =$G$16 -> 0.18918919 | W79: =1-V79 -> 0.81081081 | X79: 0 | Y79: =$H$16 -> 0.18918919 | Z79: =1-Y79 -> 0.81081081 | AA79: 0 | AB79: =$I$16 -> 0.18918919 | AC79: =1-AB79 -> 0.81081081 | AD79: 0 | AE79: =$J$16 -> 0.18918919 | AF79: =1-AE79 -> 0.81081081 | AG79: 0 | AH79: =$K$16 -> 0.18918919 | AI79: =1-AH79 -> 0.81081081 | AJ79: 0 | AK79: =$L$16 -> 0.18918919 | AL79: =1-AK79 -> 0.81081081 | AM79: 0 | AN79: =$M$16 -> 0.18918919 | AO79: =1-AN79 -> 0.81081081 | AP79: 0 | AQ79: =$N$16 -> 0.18918919 | AR79: =1-AQ79 -> 0.81081081
A80: "ichd" | B80: 4 | C80: =modAllocation!C10 -> 0 | D80: =modAllocation!D10 -> 0.2 | E80: =modAllocation!E10 -> 0.8 | F80: 0 | G80: =$B$16 -> 0.18918919 | H80: =1-G80 -> 0.81081081 | I80: 0 | J80: =$C$16 -> 0.18918919 | K80: =1-J80 -> 0.81081081 | L80: 0 | M80: =$D$16 -> 0.18918919 | N80: =1-M80 -> 0.81081081 | O80: 0 | P80: =$E$16 -> 0.18918919 | Q80: =1-P80 -> 0.81081081 | R80: 0 | S80: =$F$16 -> 0.18918919 | T80: =1-S80 -> 0.81081081 | U80: 0 | V80: =$G$16 -> 0.18918919 | W80: =1-V80 -> 0.81081081 | X80: 0 | Y80: =$H$16 -> 0.18918919 | Z80: =1-Y80 -> 0.81081081 | AA80: 0 | AB80: =$I$16 -> 0.18918919 | AC80: =1-AB80 -> 0.81081081 | AD80: 0 | AE80: =$J$16 -> 0.18918919 | AF80: =1-AE80 -> 0.81081081 | AG80: 0 | AH80: =$K$16 -> 0.18918919 | AI80: =1-AH80 -> 0.81081081 | AJ80: 0 | AK80: =$L$16 -> 0.18918919 | AL80: =1-AK80 -> 0.81081081 | AM80: 0 | AN80: =$M$16 -> 0.18918919 | AO80: =1-AN80 -> 0.81081081 | AP80: 0 | AQ80: =$N$16 -> 0.18918919 | AR80: =1-AQ80 -> 0.81081081
A81: "ichd" | B81: 5 | C81: =modAllocation!C11 -> 0 | D81: =modAllocation!D11 -> 0.2 | E81: =modAllocation!E11 -> 0.8 | F81: 0 | G81: =$B$16 -> 0.18918919 | H81: =1-G81 -> 0.81081081 | I81: 0 | J81: =$C$16 -> 0.18918919 | K81: =1-J81 -> 0.81081081 | L81: 0 | M81: =$D$16 -> 0.18918919 | N81: =1-M81 -> 0.81081081 | O81: 0 | P81: =$E$16 -> 0.18918919 | Q81: =1-P81 -> 0.81081081 | R81: 0 | S81: =$F$16 -> 0.18918919 | T81: =1-S81 -> 0.81081081 | U81: 0 | V81: =$G$16 -> 0.18918919 | W81: =1-V81 -> 0.81081081 | X81: 0 | Y81: =$H$16 -> 0.18918919 | Z81: =1-Y81 -> 0.81081081 | AA81: 0 | AB81: =$I$16 -> 0.18918919 | AC81: =1-AB81 -> 0.81081081 | AD81: 0 | AE81: =$J$16 -> 0.18918919 | AF81: =1-AE81 -> 0.81081081 | AG81: 0 | AH81: =$K$16 -> 0.18918919 | AI81: =1-AH81 -> 0.81081081 | AJ81: 0 | AK81: =$L$16 -> 0.18918919 | AL81: =1-AK81 -> 0.81081081 | AM81: 0 | AN81: =$M$16 -> 0.18918919 | AO81: =1-AN81 -> 0.81081081 | AP81: 0 | AQ81: =$N$16 -> 0.18918919 | AR81: =1-AQ81 -> 0.81081081
A82: "ichd" | B82: 6 | C82: =modAllocation!C12 -> 0 | D82: =modAllocation!D12 -> 0.2 | E82: =modAllocation!E12 -> 0.8 | F82: 0 | G82: =$B$16 -> 0.18918919 | H82: =1-G82 -> 0.81081081 | I82: 0 | J82: =$C$16 -> 0.18918919 | K82: =1-J82 -> 0.81081081 | L82: 0 | M82: =$D$16 -> 0.18918919 | N82: =1-M82 -> 0.81081081 | O82: 0 | P82: =$E$16 -> 0.18918919 | Q82: =1-P82 -> 0.81081081 | R82: 0 | S82: =$F$16 -> 0.18918919 | T82: =1-S82 -> 0.81081081 | U82: 0 | V82: =$G$16 -> 0.18918919 | W82: =1-V82 -> 0.81081081 | X82: 0 | Y82: =$H$16 -> 0.18918919 | Z82: =1-Y82 -> 0.81081081 | AA82: 0 | AB82: =$I$16 -> 0.18918919 | AC82: =1-AB82 -> 0.81081081 | AD82: 0 | AE82: =$J$16 -> 0.18918919 | AF82: =1-AE82 -> 0.81081081 | AG82: 0 | AH82: =$K$16 -> 0.18918919 | AI82: =1-AH82 -> 0.81081081 | AJ82: 0 | AK82: =$L$16 -> 0.18918919 | AL82: =1-AK82 -> 0.81081081 | AM82: 0 | AN82: =$M$16 -> 0.18918919 | AO82: =1-AN82 -> 0.81081081 | AP82: 0 | AQ82: =$N$16 -> 0.18918919 | AR82: =1-AQ82 -> 0.81081081
A83: "hhd" | B83: 1 | C83: =modAllocation!C13 -> 0.9 | D83: =modAllocation!D13 -> 0 | E83: =modAllocation!E13 -> 0.1
A84: "hhd" | B84: 2 | C84: =modAllocation!C14 -> 0.9 | D84: =modAllocation!D14 -> 0 | E84: =modAllocation!E14 -> 0.1
A85: "hhd" | B85: 3 | C85: =modAllocation!C15 -> 0.9 | D85: =modAllocation!D15 -> 0 | E85: =modAllocation!E15 -> 0.1
A86: "hhd" | B86: 4 | C86: =modAllocation!C16 -> 0.9 | D86: =modAllocation!D16 -> 0 | E86: =modAllocation!E16 -> 0.1
A87: "hhd" | B87: 5 | C87: =modAllocation!C17 -> 0.9 | D87: =modAllocation!D17 -> 0 | E87: =modAllocation!E17 -> 0.1
A88: "hhd" | B88: 6 | C88: =modAllocation!C18 -> 0.9 | D88: =modAllocation!D18 -> 0 | E88: =modAllocation!E18 -> 0.1
A89: "pd" | B89: 1 | C89: =modAllocation!C19 -> 0.98 | D89: =modAllocation!D19 -> 0.02 | E89: =modAllocation!E19 -> 0
A90: "pd" | B90: 2 | C90: =modAllocation!C20 -> 0.98 | D90: =modAllocation!D20 -> 0.02 | E90: =modAllocation!E20 -> 0
A91: "pd" | B91: 3 | C91: =modAllocation!C21 -> 0.98 | D91: =modAllocation!D21 -> 0.02 | E91: =modAllocation!E21 -> 0
A92: "pd" | B92: 4 | C92: =modAllocation!C22 -> 0.98 | D92: =modAllocation!D22 -> 0.02 | E92: =modAllocation!E22 -> 0
A93: "pd" | B93: 5 | C93: =modAllocation!C23 -> 0.98 | D93: =modAllocation!D23 -> 0.02 | E93: =modAllocation!E23 -> 0
A94: "pd" | B94: 6 | C94: =modAllocation!C24 -> 0.98 | D94: =modAllocation!D24 -> 0.02 | E94: =modAllocation!E24 -> 0
A96: Tx Type | B96: Inc | C96: Prev | F96: P(receives tx)
A97: 1 | B97: =TxType!B1 -> 0.4 | C97: =TxType!B9 -> 0.4 | E97: 1 | F97: =I49 -> 0.9
A98: 2 | B98: =TxType!B2 -> 0.25 | C98: =TxType!B10 -> 0.25 | E98: 2 | F98: =I50 -> 0.8
A99: 3 | B99: =TxType!B3 -> 0.25 | C99: =TxType!B11 -> 0.25 | E99: 3 | F99: =I51 -> 0.6
A100: 4 | B100: =TxType!B4 -> 0.25 | C100: =TxType!B12 -> 0.25 | E100: 4 | F100: =I52 -> 0.5
A101: 5 | B101: =TxType!B5 -> 0.15 | C101: =TxType!B13 -> 0.15 | E101: 5 | F101: =I53 -> 0.5
A102: 6 | B102: =TxType!B6 -> 0.02 | C102: =TxType!B14 -> 0.02 | E102: 6 | F102: =I54 -> 0.1
A105: Recieves Tx | B105: Initial | C105: 1 | D105: 2 | E105: 3 | F105: 4 | G105: 5 | H105: 6 | I105: 7 | J105: 8 | K105: 9 | L105: 10 | M105: 11 | N105: 12 | O105: 13
A106: 1 | B106: =I49 -> 0.9 | C106: =MIN(1,C122+S122) -> 0.9 | D106: =MIN(1,D122+T122) -> 0.9 | E106: =MIN(1,E122+U122) -> 0.9 | F106: =MIN(1,F122+V122) -> 0.9 | G106: =MIN(1,G122+W122) -> 0.9 | H106: =MIN(1,H122+X122) -> 0.9 | I106: =MIN(1,I122+Y122) -> 0.9 | J106: =MIN(1,J122+Z122) -> 0.9 | ... O106: =MIN(1,O122+AE122) -> 0.9
A107: 2 | B107: =I50 -> 0.8 | C107: =MIN(1,C123+S123) -> 0.8 | D107: =MIN(1,D123+T123) -> 0.8 | E107: =MIN(1,E123+U123) -> 0.8 | F107: =MIN(1,F123+V123) -> 0.8 | G107: =MIN(1,G123+W123) -> 0.8 | H107: =MIN(1,H123+X123) -> 0.8 | I107: =MIN(1,I123+Y123) -> 0.8 | J107: =MIN(1,J123+Z123) -> 0.8 | ... O107: =MIN(1,O123+AE123) -> 0.8
A108: 3 | B108: =I51 -> 0.6 | C108: =MIN(1,C124+S124) -> 0.6 | D108: =MIN(1,D124+T124) -> 0.6 | E108: =MIN(1,E124+U124) -> 0.6 | F108: =MIN(1,F124+V124) -> 0.6 | G108: =MIN(1,G124+W124) -> 0.6 | H108: =MIN(1,H124+X124) -> 0.6 | I108: =MIN(1,I124+Y124) -> 0.6 | J108: =MIN(1,J124+Z124) -> 0.6 | ... O108: =MIN(1,O124+AE124) -> 0.6 | Q108: AGE
A109: 4 | B109: =I52 -> 0.5 | C109: =MIN(1,C125+S125) -> 0.5 | D109: =MIN(1,D125+T125) -> 0.5 | E109: =MIN(1,E125+U125) -> 0.5 | F109: =MIN(1,F125+V125) -> 0.5 | G109: =MIN(1,G125+W125) -> 0.5 | H109: =MIN(1,H125+X125) -> 0.5 | I109: =MIN(1,I125+Y125) -> 0.5 | J109: =MIN(1,J125+Z125) -> 0.5 | ... O109: =MIN(1,O125+AE125) -> 0.5 | Q109: 1 | R109: 0.064097826
A110: 5 | B110: =I53 -> 0.5 | C110: =MIN(1,C126+S126) -> 0.5 | D110: =MIN(1,D126+T126) -> 0.5 | E110: =MIN(1,E126+U126) -> 0.5 | F110: =MIN(1,F126+V126) -> 0.5 | G110: =MIN(1,G126+W126) -> 0.5 | H110: =MIN(1,H126+X126) -> 0.5 | I110: =MIN(1,I126+Y126) -> 0.5 | J110: =MIN(1,J126+Z126) -> 0.5 | ... O110: =MIN(1,O126+AE126) -> 0.5 | Q110: 2 | R110: 0.078136542
A111: 6 | B111: =I54 -> 0.1 | C111: =MIN(1,C127+S127) -> 0.1 | D111: =MIN(1,D127+T127) -> 0.1 | E111: =MIN(1,E127+U127) -> 0.1 | F111: =MIN(1,F127+V127) -> 0.1 | G111: =MIN(1,G127+W127) -> 0.1 | H111: =MIN(1,H127+X127) -> 0.1 | I111: =MIN(1,I127+Y127) -> 0.1 | J111: =MIN(1,J127+Z127) -> 0.1 | ... O111: =MIN(1,O127+AE127) -> 0.1 | Q111: 3 | R111: 0.13022758
Q112: 4 | R112: 0.17160485
A113: TxType | B113: Initial | C113: 1 | D113: 2 | E113: 3 | F113: 4 | G113: 5 | H113: 6 | I113: 7 | J113: 8 | K113: 9 | L113: 10 | M113: 11 | N113: 12 | O113: 13 | Q113: 5 | R113: 0.23341214
...

Sheet Scenario Inputs
C14: Model Parameters
C16: Select Model Parameters | N16: Set Intervention Time Parameters
C18: Select the region and centre of interest. To perform a region level run select "All" on the centre drop down. The default incidence profile is CKD Baseline (from the system dynamics model of disease progression). Other options represent special scenarios run with the CKD model. Baseline is a simple linear projection. | N18: Select the year the intervention is planned to take place. The change is in place from Jan 1st that year. The simulation will run from the start of "run start year" to the end of "run end year". Both are fixed inputs. Note: Dec 31st 2022 is the last observed date in the UKRR data, the model is initialised accordingly.
C20: Region | F20: Fictional Region
C21: Centre | F21: Fictional Centre | N21: Run start year | R21: 2023
C22: Ethnicity | F22: Baseline
C23: Incidence Profile | F23: CKD baseline | N23: Run end year | R23: 2035
N25: Intervention Selection Summary (Of changes made below): | T25: Default Estimate | V25: New Value (Result of user input)
N26: =C49 -> Change in % allocated to HHD | T26: =G49 -> 0.18918919 | V26: =K49 -> 0
N27: =C52 -> Change in % initially allocated to PD | T27: =G52 -> 0.29 | V27: =K52 -> 0
N28: =#REF! -> #REF! | T28: =#REF! -> #REF! | V28: =#REF! -> #REF!
N29: =#REF! -> #REF! | T29: =#REF! -> #REF! | V29: =#REF! -> #REF!
N30: =C91 -> Change to % of patients receiving a transplant | T30: =G91 -> 0.9 | V30: =K91 -> 0
N31: =C94 -> 0 | T31: =G94 -> 0.5 | V31: =K94 -> 0
C33: Centre based growth assumption
C35: Centre based growth assumption: The baseline assumption is that incidence to KRT for a centre grows as a constant proportion of regional growth. This can be edited here to reflect a non-stationary profile of growth for a centre.
G36: Current Value (Default) | I36: Year
I37: 2023 | J37: 2024 | K37: 2025 | L37: 2026 | M37: 2027 | N37: 2028 | O37: 2029 | P37: 2030 | Q37: 2031 | R37: 2032 | S37: 2033 | T37: 2034 | U37: 2035
C38: Centre based growth assumption | G38: 1
G39: Default Incidence: | I39: =daily_rate!N2 -> 0.5 | J39: =daily_rate!O2 -> 0.5 | K39: =daily_rate!P2 -> 0.5 | L39: =daily_rate!Q2 -> 0.5 | M39: =daily_rate!R2 -> 0.5 | N39: =daily_rate!S2 -> 0.5 | O39: =daily_rate!T2 -> 0.5 | P39: =daily_rate!U2 -> 0.5 | ... U39: =daily_rate!Z2 -> 0.5
G40: User Impacted Incidence: | I40: =simPy_sheet!B6 -> 0.5 | J40: =simPy_sheet!C6 -> 0.5 | K40: =simPy_sheet!D6 -> 0.5 | L40: =simPy_sheet!E6 -> 0.5 | M40: =simPy_sheet!F6 -> 0.5 | N40: =simPy_sheet!G6 -> 0.5 | O40: =simPy_sheet!H6 -> 0.5 | P40: =simPy_sheet!I6 -> 0.5 | ... U40: =simPy_sheet!N6 -> 0.5
C41: Interventions
C43: Change in HHD and/or PD allocation | Y43: Reference Values
C45: Change in HHD: Allows a user to change the percentage of people on HHD to a target of x% at the end of each year (to achieve this patients are moved from/to ICHD). Change in PD: Allows a user to change the initial allocation probablity of PD to a target of x% (resulting in shifting the initial ICHD allocation probability up or down). | Y45: The following plots are for reference when setting new scenario values. Values are provided at national (England), regional (Midlands) and centre levels. This should allow a user to pick an optimistic, but realistic scenario value.
G47: Current Value (Default) | I47: Rollout year target percentage
I48: =R21 -> 2023 | J48: =I48+1 -> 2024 | K48: =J48+1 -> 2025 | L48: =K48+1 -> 2026 | M48: =L48+1 -> 2027 | N48: =M48+1 -> 2028 | O48: =N48+1 -> 2029 | P48: =O48+1 -> 2030 | Q48: =P48+1 -> 2031 | ... U48: =T48+1 -> 2035
C49: Change in % allocated to HHD | G49: =simPy_sheet!B257 -> 0.18918919
G50: Default Allocation %: | I50: =IncHHD -> 0.18918919 | J50: =IncHHD -> 0.18918919 | K50: =IncHHD -> 0.18918919 | L50: =IncHHD -> 0.18918919 | M50: =IncHHD -> 0.18918919 | N50: =IncHHD -> 0.18918919 | O50: =IncHHD -> 0.18918919 | P50: =IncHHD -> 0.18918919 | ... U50: =IncHHD -> 0.18918919
G51: User Impacted Allocation %: | I51: =AVERAGE(simPy_sheet!G77:G82) -> 0.18918919 | J51: =AVERAGE(simPy_sheet!J77:J82) -> 0.18918919 | K51: =AVERAGE(simPy_sheet!M77:M82) -> 0.18918919 | L51: =AVERAGE(simPy_sheet!P77:P82) -> 0.18918919 | M51: =AVERAGE(simPy_sheet!S77:S82) -> 0.18918919 | N51: =AVERAGE(simPy_sheet!V77:V82) -> 0.18918919 | O51: =AVERAGE(simPy_sheet!Y77:Y82) -> 0.18918919 | P51: =AVERAGE(simPy_sheet!AB77:AB82) -> 0.18918919 | Q51: =AVERAGE(simPy_sheet!AE77:AE82) -> 0.18918919 | R51: =AVERAGE(simPy_sheet!AH77:AH82) -> 0.18918919 | S51: =AVERAGE(simPy_sheet!AK77:AK82) -> 0.18918919 | T51: =AVERAGE(simPy_sheet!AN77:AN82) -> 0.18918919 | U51: =AVERAGE(simPy_sheet!AQ77:AQ82) -> 0.18918919
C52: Change in % initially allocated to PD | G52: =modAllocation!E1 -> 0.29
G53: Default Allocation %: | I53: =AVERAGE(simPy_sheet!$E$71:$E$76) -> 0.29 | J53: =AVERAGE(simPy_sheet!$E$71:$E$76) -> 0.29 | K53: =AVERAGE(simPy_sheet!$E$71:$E$76) -> 0.29 | L53: =AVERAGE(simPy_sheet!$E$71:$E$76) -> 0.29 | M53: =AVERAGE(simPy_sheet!$E$71:$E$76) -> 0.29 | N53: =AVERAGE(simPy_sheet!$E$71:$E$76) -> 0.29 | O53: =AVERAGE(simPy_sheet!$E$71:$E$76) -> 0.29 | P53: =AVERAGE(simPy_sheet!$E$71:$E$76) -> 0.29 | ... U53: =AVERAGE(simPy_sheet!$E$71:$E$76) -> 0.29
G54: User Impacted Allocation %: | I54: =AVERAGE(simPy_sheet!H71:H76) -> 0.29 | J54: =AVERAGE(simPy_sheet!K71:K76) -> 0.29 | K54: =AVERAGE(simPy_sheet!N71:N76) -> 0.29 | L54: =AVERAGE(simPy_sheet!Q71:Q76) -> 0.29 | M54: =AVERAGE(simPy_sheet!T71:T76) -> 0.29 | N54: =AVERAGE(simPy_sheet!W71:W76) -> 0.29 | O54: =AVERAGE(simPy_sheet!Z71:Z76) -> 0.29 | P54: =AVERAGE(simPy_sheet!AC71:AC76) -> 0.29 | Q54: =AVERAGE(simPy_sheet!AF71:AF76) -> 0.29 | R54: =AVERAGE(simPy_sheet!AI71:AI76) -> 0.29 | S54: =AVERAGE(simPy_sheet!AL71:AL76) -> 0.29 | T54: =AVERAGE(simPy_sheet!AO71:AO76) -> 0.29 | U54: =AVERAGE(simPy_sheet!AR71:AR76) -> 0.29
C55: Diversion to CC and/or reductions in late presentations
C57: Change in divert to conservative care: A relative change in the proportion of all age groups that are diverted to conservative management/care by x%. This is applied equally across all age groups. Change in late presentation: A relative change in the proportion of patients that present to the system late.
G59: Current Value (Default) | I59: Rollout year target percentage
F60: Age group | I60: =R21 -> 2023 | J60: =I60+1 -> 2024 | K60: =J60+1 -> 2025 | L60: =K60+1 -> 2026 | M60: =L60+1 -> 2027 | N60: =M60+1 -> 2028 | O60: =N60+1 -> 2029 | P60: =O60+1 -> 2030 | Q60: =P60+1 -> 2031 | ... U60: =T60+1 -> 2035
C61: Change in probability of diverting to conservative care | F61: 16-35 | G61: =divertToCC!C1 -> 0.1
F62: 36-45 | G62: =divertToCC!C2 -> 0.1
F63: 46-55 | G63: =divertToCC!C3 -> 0.1
F64: 56-65 | G64: =divertToCC!C4 -> 0.1
F65: 66-75 | G65: =divertToCC!C5 -> 0.25
F66: 75+ | G66: =divertToCC!C6 -> 0.5
C67: Change in probability of late presentation | G67: =referral_dist!B2 -> 0.2
G68: Default percentage late presenters: | I68: =IncLP -> 0.2 | J68: =IncLP -> 0.2 | K68: =IncLP -> 0.2 | L68: =IncLP -> 0.2 | M68: =IncLP -> 0.2 | N68: =IncLP -> 0.2 | O68: =IncLP -> 0.2 | P68: =IncLP -> 0.2 | ... U68: =IncLP -> 0.2
G69: User Impacted percentage late presenters: | I69: =simPy_sheet!B12 -> 0.2 | J69: =simPy_sheet!C12 -> 0.2 | K69: =simPy_sheet!D12 -> 0.2 | L69: =simPy_sheet!E12 -> 0.2 | M69: =simPy_sheet!F12 -> 0.2 | N69: =simPy_sheet!G12 -> 0.2 | O69: =simPy_sheet!H12 -> 0.2 | P69: =simPy_sheet!I12 -> 0.2 | ... U69: =simPy_sheet!N12 -> 0.2
C71: Transplant Interventions
C73: Change in % of patients receiving a live transplant: Allows a user to change the percentage of patients that receiving a live transplant given that they were listed. This change is applied enely across age groups. Change in % of patients receiving a cadaver transplant: Allows a user to change the percentage of patients that receiving a cadaver transplant given that they were listed. This change is applied evenly across age groups. Change in % of transplant patients receiving pre-emptive transplants: Allows a user to change the percentage of patients with early referral status that receive a pre-emptive (preE) transplant. This change is applied proportionally across transplant types.
G75: Current Value (Default) | I75: 2023 | J75: 2024 | K75: 2025 | L75: 2026 | M75: 2027 | N75: 2028 | O75: 2029 | P75: 2030 | Q75: 2031 | R75: 2032 | S75: 2033 | T75: 2034 | U75: 2035
C76: Change to % of listed patients receiving a live transplant | G76: =simPy_sheet!B128 -> 0.097838221
G77: Default % patients receiveing a transplant: | I77: =$G$76 -> 0.097838221 | J77: =$G$76 -> 0.097838221 | K77: =$G$76 -> 0.097838221 | L77: =$G$76 -> 0.097838221 | M77: =$G$76 -> 0.097838221 | N77: =$G$76 -> 0.097838221 | O77: =$G$76 -> 0.097838221 | P77: =$G$76 -> 0.097838221 | ... U77: =$G$76 -> 0.097838221
G78: User Impacted % of patients receiving a transplant: | I78: =simPy_sheet!C128 -> 0.097838221 | J78: =simPy_sheet!D128 -> 0.097838221 | K78: =simPy_sheet!E128 -> 0.097838221 | L78: =simPy_sheet!F128 -> 0.097838221 | M78: =simPy_sheet!G128 -> 0.097838221 | N78: =simPy_sheet!H128 -> 0.097838221 | O78: =simPy_sheet!I128 -> 0.097838221 | P78: =simPy_sheet!J128 -> 0.097838221 | ... U78: =simPy_sheet!O128 -> 0.097838221
C79: Change to % of listed patients receiving a cadaver transplant | G79: =simPy_sheet!R128 -> 0.3352562
G80: Default % patients receiveing a transplant: | I80: =$G$79 -> 0.3352562 | J80: =$G$79 -> 0.3352562 | K80: =$G$79 -> 0.3352562 | L80: =$G$79 -> 0.3352562 | M80: =$G$79 -> 0.3352562 | N80: =$G$79 -> 0.3352562 | O80: =$G$79 -> 0.3352562 | P80: =$G$79 -> 0.3352562 | ... U80: =$G$79 -> 0.3352562
G81: User Impacted % of patients receiving a transplant: | I81: =AVERAGE(simPy_sheet!S128) -> 0.3352562 | J81: =AVERAGE(simPy_sheet!T128) -> 0.3352562 | K81: =AVERAGE(simPy_sheet!U128) -> 0.3352562 | L81: =AVERAGE(simPy_sheet!V128) -> 0.3352562 | M81: =AVERAGE(simPy_sheet!W128) -> 0.3352562 | N81: =AVERAGE(simPy_sheet!X128) -> 0.3352562 | O81: =AVERAGE(simPy_sheet!Y128) -> 0.3352562 | P81: =AVERAGE(simPy_sheet!Z128) -> 0.3352562 | ... U81: =AVERAGE(simPy_sheet!AE128) -> 0.3352562
C82: Change to % of Tx patients that have preE-Tx | G82: =AVERAGE(simPy_sheet!$AI$57:$AI$62) -> 0.2
G83: Default % Tx patients receiveing a preE transplant: | I83: =$G$82 -> 0.2 | J83: =$G$82 -> 0.2 | K83: =$G$82 -> 0.2 | L83: =$G$82 -> 0.2 | M83: =$G$82 -> 0.2 | N83: =$G$82 -> 0.2 | O83: =$G$82 -> 0.2 | P83: =$G$82 -> 0.2 | ... U83: =$G$82 -> 0.2
G84: User Impacted % of Tx patients receiving a preE transplant: | I84: =AVERAGE(simPy_sheet!AJ57:AJ62) -> 0.2 | J84: =AVERAGE(simPy_sheet!AK57:AK62) -> 0.2 | K84: =AVERAGE(simPy_sheet!AL57:AL62) -> 0.2 | L84: =AVERAGE(simPy_sheet!AM57:AM62) -> 0.2 | M84: =AVERAGE(simPy_sheet!AN57:AN62) -> 0.2 | N84: =AVERAGE(simPy_sheet!AO57:AO62) -> 0.2 | O84: =AVERAGE(simPy_sheet!AP57:AP62) -> 0.2 | P84: =AVERAGE(simPy_sheet!AQ57:AQ62) -> 0.2 | ... U84: =AVERAGE(simPy_sheet!AV57:AV62) -> 0.2
C86: Transplant Interventions
C88: Change in % of patients receiving a transplant: Allows a user to change the percentage of patients that receiving a transplant after having been listed. This change is applied proportionally across age groups. Change in pre-emptive transplants: Allows a user to change the percentage of patients with early referral status that receive a pre-emptive (preE) transplant. This change is applied proportionally across transplant types.
I89: Rollout year target/target percentage
F90: Age group | G90: Current Value (Default) | I90: =R21 -> 2023 | J90: =I90+1 -> 2024 | K90: =J90+1 -> 2025 | L90: =K90+1 -> 2026 | M90: =L90+1 -> 2027 | N90: =M90+1 -> 2028 | O90: =N90+1 -> 2029 | P90: =O90+1 -> 2030 | Q90: =P90+1 -> 2031 | ... U90: =T90+1 -> 2035
C91: Change to % of patients receiving a transplant | F91: 16-35 | G91: =receivesTx!B1 -> 0.9
F92: 36-45 | G92: =receivesTx!B2 -> 0.8
F93: 46-55 | G93: =receivesTx!B3 -> 0.6
F94: 56-65 | G94: =receivesTx!B4 -> 0.5
F95: 66-75 | G95: =receivesTx!B5 -> 0.5
F96: 75+ | G96: =receivesTx!B6 -> 0.1
C98: New CKD Scenario | F98: HIDE THIS TEST | H98: =IF(F23 = "New CKD Scenario", 0, 1) -> 1
C99: Change to % of Tx patients that have preE-Tx | G99: =AVERAGE(simPy_sheet!AI57:AI62) -> 0.2
C101: New CKD Scenario | F101: HIDE THIS TEST | H101: =IF(F23 = "New CKD Scenario", 0, 1) -> 1
C103: New CKD Scenario: If an alternative scenario has been run using the CKD model and you would like to use that as an input to this model then input it below. Note that the input takes an annual number of arrivals and coverts it to daily (with an inflation factor for conservative management patients that aren't accounted for in the CKD output). Note: The CKD model output is regional. This will be adjusted to centre level, and to account for the population diverting to conservative care, automatically before the simulation is run. The adjusted profile can be seen below your input.
F105: 2023 | G105: 2024 | H105: 2025 | I105: 2026 | J105: 2027 | K105: 2028 | L105: 2029 | M105: 2030 | N105: 2031 | O105: 2032 | P105: 2033 | Q105: 2034 | R105: 2035
C106: Default Incidence Profile | F106: =simPy_sheet!B5 -> 0.5 | G106: =simPy_sheet!C5 -> 0.5 | H106: =simPy_sheet!D5 -> 0.5 | I106: =simPy_sheet!E5 -> 0.5 | J106: =simPy_sheet!F5 -> 0.5 | K106: =simPy_sheet!G5 -> 0.5 | L106: =simPy_sheet!H5 -> 0.5 | M106: =simPy_sheet!I5 -> 0.5 | ... R106: =simPy_sheet!N5 -> 0.5
C107: New (Regional) Annual Incidence Profile from CKD
C108: Adjusted incidence profile | F108: =IF(F107>0,daily_rate!N2,"") | G108: =IF(G107>0,daily_rate!O2,"") | H108: =IF(H107>0,daily_rate!P2,"") | I108: =IF(I107>0,daily_rate!Q2,"") | J108: =IF(J107>0,daily_rate!R2,"") | K108: =IF(K107>0,daily_rate!S2,"") | L108: =IF(L107>0,daily_rate!T2,"") | M108: =IF(M107>0,daily_rate!U2,"") | ... R108: =IF(R107>0,daily_rate!Z2,"")
J109: ERROR: Probability must be between 0-1. | O109: =IF(P107>0,daily_rate!X4,"")

Sheet Cost Inputs
C12: Model Cost Parameters
C14: Average annual costs by treatment pathways per patient | O14: Costing Summary
C16: Default cost inputs are provided here based on costs from the Intercept paper. These can be edited by the user to reflect area specific or updated costing estimates as appropriate. | O16: Default cost inputs are provided here based on costs from the Intercept paper. These can be edited by the user to reflect area specifc or updated costing estimates as appropriate.
G17: Default Model Cost | I17: Adjusted Cost | K17: New Value (Result of user input) | U17: Default Model Cost | W17: New Value (Result of user input) | Z17: HIDE THIS
C18: Annual average cost of ICHD | G18: 62842.05 | K18: =IF(I18="", G18, I18) -> 62842.05 | O18: Treatment Pathway Costs | Q18: Annual average cost of ICHD | U18: 62842.05 | W18: =K18 -> 62842.05 | Z18: =U18 -> 62842.05 | AA18: =W18 -> 62842.05
C19: Annual average cost of HHD | G19: 51121.9 | K19: =IF(I19="", G19, I19) -> 51121.9 | Q19: Annual average cost of HHD | U19: 51121.9 | W19: =K19 -> 51121.9 | Z19: =U19 -> 51121.9 | AA19: =W19 -> 51121.9
C20: Annual average cost of PD | G20: 39390.8 | K20: =IF(I20="", G20, I20) -> 39390.8 | Q20: Annual average cost of PD | U20: 39390.8 | W20: =K20 -> 39390.8 | Z20: =U20 -> 39390.8 | AA20: =W20 -> 39390.8
C21: Annual average cost of Living with Tx | G21: 9004.55 | K21: =IF(I21="", G21, I21) -> 9004.55 | Q21: Annual average cost of Living with Tx | U21: 9004.55 | W21: =K21 -> 9004.55 | Z21: =U21 -> 9004.55 | AA21: =W21 -> 9004.55
J22: ERROR: Cost must be positive above zero. | O22: Intervention Costs | Q22: =E36 -> Intervention 1: KRT intervention | U22: 0 | W22: =V36 -> 0 | Z22: =U22 -> 0 | AA22: =W22 -> 0
Q23: =E37 -> Intervention 2: KRT intervention | U23: 0 | W23: =V37 -> 0 | Z23: =U23 -> 0 | AA23: =W23 -> 0
Q24: =E38 -> Intervention 3: KRT intervention | U24: 0 | W24: =V38 -> 0 | Z24: =U24 -> 0 | AA24: =W24 -> 0
Q25: =E39 -> Intervention 4 | U25: 0 | W25: =V39 -> 0 | Z25: =U25 -> 0 | AA25: =W25 -> 0
Q26: =E40 -> Intervention 5 | U26: 0 | W26: =V40 -> 0 | Z26: =U26 -> 0 | AA26: =W26 -> 0
Q27: All Interventions Total Cost | U27: 0 | W27: =V41 -> 0 | Z27: =U27 -> 0 | AA27: =W27 -> 0
C29: Intervention Costs
E33: Optional: Write in Name of Program / intervention | I33: 2023 | J33: 2024 | K33: 2025 | L33: 2026 | M33: 2027 | N33: 2028 | O33: 2029 | P33: 2030 | Q33: 2031 | R33: 2032 | S33: 2033 | T33: 2034 | U33: 2035 | V33: Total Intervention / Program Cost
E34: Example: CKT/primary care interventions costs | N34: 10000 | O34: 5000 | P34: 5000 | V34: =SUM(I34:U34) -> 20000
E35: Example: KRT/secondary care interventions costs | M35: 50000 | N35: 500 | O35: 500 | P35: 500 | Q35: 10500 | R35: 500 | S35: 500 | T35: 500 | U35: 500 | V35: =SUM(I35:U35) -> 64000
C36: Intervention 1 | E36: Intervention 1: KRT intervention | V36: =SUM(I36:U36) -> 0
C37: Intervention 2 | E37: Intervention 2: KRT intervention | V37: =SUM(I37:U37) -> 0
C38: Intervention 3 | E38: Intervention 3: KRT intervention | V38: =SUM(I38:U38) -> 0
C39: Intervention 4 | E39: Intervention 4 | V39: =SUM(I39:U39) -> 0
C40: Intervention 5 | E40: Intervention 5 | V40: =SUM(I40:U40) -> 0
C41: All interventions (adjusted) | E41: All above interventions | I41: =SUM(I36:I38) -> 0 | J41: =SUM(J36:J38) -> 0 | K41: =SUM(K36:K38) -> 0 | L41: =SUM(L36:L38) -> 0 | M41: =SUM(M36:M38) -> 0 | N41: =SUM(N36:N38) -> 0 | O41: =SUM(O36:O38) -> 0 | P41: =SUM(P36:P38) -> 0 | ... U41: =SUM(U36:U38) -> 0 | V41: =SUM(I41:U41) -> 0
B97: =TxType!B1 -> 0.4
A98: 1 | B98: =TxType!B2 -> 0.25
A99: 2 | B99: =TxType!B3 -> 0.25
A100: 3 | B100: =TxType!B4 -> 0.25
A101: 4 | B101: =TxType!B5 -> 0.15
A102: 5 | B102: =TxType!B6 -> 0.02

Sheet References

Sheet Hide Selection Settings
A1: Region | B1: Unit | C1: Incidence | E1: Unit | F1: Unit population proportions (for incidence profile conversion)
A2: Fictional Region | B2: Fictional Centre | C2: CKD baseline | E2: Fictional Centre | F2: 1
C3: New CKD Scenario

Sheet Prev_Pop_Initialisation
A1: Initialisation | C1: Validation | D1: Experimentation
A2: concare
B3: 1_early: | C3: 0 | D3: 0
B4: 2_early: | C4: 0 | D4: 0
B5: 3_early: | C5: 0 | D5: 0
B6: 4_early: | C6: 0 | D6: 0
B7: 5_early: | C7: 0 | D7: 0
B8: 6_early: | C8: 0 | D8: 0
B9: 1_late: | C9: 0 | D9: 0
B10: 2_late: | C10: 0 | D10: 0
B11: 3_late: | C11: 0 | D11: 0
B12: 4_late: | C12: 0 | D12: 0
B13: 5_late: | C13: 0 | D13: 0
B14: 6_late: | C14: 0 | D14: 0
A16: ichd:
B17: 1_early: | C17: 10 | D17: 20
B18: 2_early: | C18: 10 | D18: 20
B19: 3_early: | C19: 10 | D19: 20
B20: 4_early: | C20: 10 | D20: 20
B21: 5_early: | C21: 10 | D21: 20
B22: 6_early: | C22: 10 | D22: 20
B23: 1_late: | C23: 10 | D23: 20
B24: 2_late: | C24: 10 | D24: 20
B25: 3_late: | C25: 10 | D25: 20
B26: 4_late: | C26: 10 | D26: 20
B27: 5_late: | C27: 10 | D27: 20
B28: 6_late: | C28: 10 | D28: 20
A30: hhd:
B31: 1_early: | C31: 1 | D31: 7
B32: 2_early: | C32: 1 | D32: 7
B33: 3_early: | C33: 1 | D33: 7
B34: 4_early: | C34: 1 | D34: 7
B35: 5_early: | C35: 1 | D35: 7
B36: 6_early: | C36: 1 | D36: 7
B37: 1_late: | C37: 1 | D37: 7
B38: 2_late: | C38: 1 | D38: 7
B39: 3_late: | C39: 1 | D39: 7
B40: 4_late: | C40: 1 | D40: 7
B41: 5_late: | C41: 1 | D41: 7
B42: 6_late: | C42: 1 | D42: 7
A44: pd:
B45: 1_early: | C45: 7 | D45: 10
B46: 2_early: | C46: 7 | D46: 10
B47: 3_early: | C47: 7 | D47: 10
B48: 4_early: | C48: 7 | D48: 10
B49: 5_early: | C49: 7 | D49: 10
B50: 6_early: | C50: 7 | D50: 10
B51: 1_late: | C51: 7 | D51: 10
B52: 2_late: | C52: 7 | D52: 10
B53: 3_late: | C53: 7 | D53: 10
B54: 4_late: | C54: 7 | D54: 10
B55: 5_late: | C55: 7 | D55: 10
B56: 6_late: | C56: 7 | D56: 10
A58: live_transplant:
B59: 1_early: | C59: 3 | D59: 10
B60: 2_early: | C60: 3 | D60: 10
B61: 3_early: | C61: 3 | D61: 10
B62: 4_early: | C62: 3 | D62: 10
B63: 5_early: | C63: 3 | D63: 10
B64: 6_early: | C64: 3 | D64: 10
B65: 1_late: | C65: 3 | D65: 10
B66: 2_late: | C66: 3 | D66: 10
B67: 3_late: | C67: 3 | D67: 10
B68: 4_late: | C68: 3 | D68: 10
B69: 5_late: | C69: 3 | D69: 10
B70: 6_late: | C70: 3 | D70: 10
A72: cadaver_transplant:
B73: 1_early: | C73: 10 | D73: 25
B74: 2_early: | C74: 10 | D74: 25
B75: 3_early: | C75: 10 | D75: 25
B76: 4_early: | C76: 10 | D76: 25
B77: 5_early: | C77: 10 | D77: 25
B78: 6_early: | C78: 10 | D78: 25
B79: 1_late: | C79: 10 | D79: 25
B80: 2_late: | C80: 10 | D80: 25
B81: 3_late: | C81: 10 | D81: 25
B82: 4_late: | C82: 10 | D82: 25
B83: 5_late: | C83: 10 | D83: 25
B84: 6_late: | C84: 10 | D84: 25

Sheet age_dist
A1: 1 | B1: 0.05
A2: 2 | B2: 0.07
A3: 3 | B3: 0.12
A4: 4 | B4: 0.2
A5: 5 | B5: 0.25
A6: 6 | B6: =1-SUM(B1:B5) -> 0.31

Sheet referral_dist
A1: Early | B1: 0.8
A2: Late | B2: 0.2

Sheet daily_rate
A1: 2010 | B1: 2011 | C1: 2012 | D1: 2013 | E1: 2014 | F1: 2015 | G1: 2016 | H1: 2017 | I1: 2018 | J1: 2019 | K1: 2020 | L1: 2021 | M1: 2022 | N1: 2023 | O1: 2024 | P1: 2025 | Q1: 2026 | R1: 2027 | S1: 2028 | T1: 2029 | U1: 2030 | V1: 2031 | W1: 2032 | X1: 2033 | Y1: 2034 | Z1: 2035
A2: 0.5 | B2: 0.5 | C2: 0.5 | D2: 0.5 | E2: 0.5 | F2: 0.5 | G2: 0.5 | H2: 0.5 | I2: 0.5 | J2: 0.5 | K2: 0.5 | L2: 0.5 | M2: 0.5 | N2: =IF('Scenario Inputs'!F107>0,'Scenario Inputs'!F107/365,0.5) -> 0.5 | O2: =IF('Scenario Inputs'!G107>0,'Scenario Inputs'!G107/365,0.5) -> 0.5 | P2: =IF('Scenario Inputs'!H107>0,'Scenario Inputs'!H107/365,0.5) -> 0.5 | Q2: =IF('Scenario Inputs'!I107>0,'Scenario Inputs'!I107/365,0.5) -> 0.5 | R2: =IF('Scenario Inputs'!J107>0,'Scenario Inputs'!J107/365,0.5) -> 0.5 | S2: =IF('Scenario Inputs'!K107>0,'Scenario Inputs'!K107/365,0.5) -> 0.5 | T2: =IF('Scenario Inputs'!L107>0,'Scenario Inputs'!L107/365,0.5) -> 0.5 | U2: =IF('Scenario Inputs'!M107>0,'Scenario Inputs'!M107/365,0.5) -> 0.5 | ... Z2: =IF('Scenario Inputs'!R107>0,'Scenario Inputs'!R107/365,0.5) -> 0.5 | XFD2: =VLOOKUP(#REF!,INDIRECT("daily_rate_profiles_all_models!$B$" &#REF!):INDIRECT("daily_rate_profiles_all_models!$AB$" &#REF!),23,TRUE) -> #REF!

Sheet divertToCC
A1: 1 | B1: 1 | C1: 0.1
A2: 2 | B2: 2 | C2: 0.1
A3: 3 | B3: 3 | C3: 0.1
A4: 4 | B4: 4 | C4: 0.1
A5: 5 | B5: 5 | C5: 0.25
A6: 6 | B6: 6 | C6: 0.5

Sheet suitableForTx
A1: 1 | B1: 0.7 | C1: Incident
A2: 2 | B2: 0.6
A3: 3 | B3: 0.5
A4: 4 | B4: 0.4
A5: 5 | B5: 0.2
A6: 6 | B6: 0.05
A9: 1 | B9: 0.7 | C9: Prevalent
A10: 2 | B10: 0.6
A11: 3 | B11: 0.5
A12: 4 | B12: 0.4
A13: 5 | B13: 0.2
A14: 6 | B14: 0.05

Sheet preE_Tx_Cadav
A1: Early | B1: 1 | C1: 0.1
A2: Early | B2: 2 | C2: 0.1
A3: Early | B3: 3 | C3: 0.1
A4: Early | B4: 4 | C4: 0.1
A5: Early | B5: 5 | C5: 0.1
A6: Early | B6: 6 | C6: 0.1
A7: Late | B7: 1 | C7: 0
A8: Late | B8: 2 | C8: 0
A9: Late | B9: 3 | C9: 0
A10: Late | B10: 4 | C10: 0
A11: Late | B11: 5 | C11: 0
A12: Late | B12: 6 | C12: 0

Sheet preE_Tx_Live
A1: Early | B1: 1 | C1: 0.3
A2: Early | B2: 2 | C2: 0.3
A3: Early | B3: 3 | C3: 0.3
A4: Early | B4: 4 | C4: 0.3
A5: Early | B5: 5 | C5: 0.3
A6: Early | B6: 6 | C6: 0.3
A7: Late | B7: 1 | C7: 0
A8: Late | B8: 2 | C8: 0
A9: Late | B9: 3 | C9: 0
A10: Late | B10: 4 | C10: 0
A11: Late | B11: 5 | C11: 0
A12: Late | B12: 6 | C12: 0

Sheet modAllocation
A1: "none" | B1: 1 | C1: 0.69 | D1: 0.02 | E1: 0.29
A2: "none" | B2: 2 | C2: 0.69 | D2: 0.02 | E2: 0.29
A3: "none" | B3: 3 | C3: 0.69 | D3: 0.02 | E3: 0.29
A4: "none" | B4: 4 | C4: 0.69 | D4: 0.02 | E4: 0.29
A5: "none" | B5: 5 | C5: 0.69 | D5: 0.02 | E5: 0.29
A6: "none" | B6: 6 | C6: 0.69 | D6: 0.02 | E6: 0.29
A7: "ichd" | B7: 1 | C7: 0 | D7: 0.2 | E7: 0.8
A8: "ichd" | B8: 1 | C8: 0 | D8: 0.2 | E8: 0.8
A9: "ichd" | B9: 1 | C9: 0 | D9: 0.2 | E9: 0.8
A10: "ichd" | B10: 1 | C10: 0 | D10: 0.2 | E10: 0.8
A11: "ichd" | B11: 2 | C11: 0 | D11: 0.2 | E11: 0.8
A12: "ichd" | B12: 2 | C12: 0 | D12: 0.2 | E12: 0.8
... A24: "pd" | B24: 5 | C24: 0.98 | D24: 0.02 | E24: 0

Sheet TxType
A1: 1 | B1: 0.4
A2: 2 | B2: 0.25
A3: 3 | B3: 0.25
A4: 4 | B4: 0.25
A5: 5 | B5: 0.15
A6: 6 | B6: 0.02
A9: 1 | B9: 0.4
A10: 2 | B10: 0.25
A11: 3 | B11: 0.25
A12: 4 | B12: 0.25
A13: 5 | B13: 0.15
A14: 6 | B14: 0.02

Sheet receivesTx
A1: 1 | B1: 0.9
A2: 2 | B2: 0.8
A3: 3 | B3: 0.6
A4: 4 | B4: 0.5
A5: 5 | B5: 0.5
A6: 6 | B6: 0.1
A9: 1 | B9: 0.6
A10: 2 | B10: 0.3
A11: 3 | B11: 0.3
A12: 4 | B12: 0.3
A13: 5 | B13: 0.15
A14: 6 | B14: 0.1
